[{"file_id": "19bc86d438fd4d06b14a99c32595b0ad", "article": "Chunk # 0.\n# Bibliography Recommendation Report\n\n## Research Question\nHow can we create or mimic the essential cellular conditions that support mitochondrial functions, such as ATP production, outside of the cellular environment \n## Introduction\nMitochondria are the powerhouses of the cell, responsible for the production of adenosine triphosphate (ATP), the primary energy currency in biological systems Understanding and replicating mitochondrial functions outside of the cellular environment is crucial for various applications, including synthetic biology, disease modeling, and therapeutic interventions This report analyzes several sources that contribute to our understanding of mitochondrial ATP production and the potential for its replication ex vivo \n## Recommended Sources\n\n### 1 A Thermodynamically-Consistent Model for ATP Production in Mitochondria\n**Source URL**: [bioRxiv](https://www.biorxiv.org/content/10.1101/2022.08.16.500715v1)\n\n**Relevance**: This preprint presents a thermodynamically consistent model for ATP production in mitochondria, which is crucial for understanding the conditions necessary for ATP synthesis outside of a cellular environment The model accounts for reaction rate constants and their dependence on factors such as membrane potential, pH, and substrate concentrations \n**Reliability**: As a preprint, this source has not undergone peer review, which may affect its reliability However, the detailed balance and thermodynamic considerations suggest a rigorous approach to modeling mitochondrial ATP production \n**Significance**: The model's ability to simulate ATP production rates and link them to mitochondrial morphology provides insights into the structural and environmental conditions necessary for ATP synthesis This could guide the design of artificial systems that replicate mitochondrial functions \n### 2 Artificial Organelles for Sustainable Chemical Energy Conversion and Production\n**Source URL**: [Phys.org](https://phys.org/news/2023-03-powerhouse-future-artificial-cells.html)\n\n**Relevance**: This article discusses the challenges and future directions in creating artificial cells with biologically realistic energy-generation methods It emphasizes the importance of self-adaptation in changing environments to maintain a stable ATP supply \n**Reliability**: The article is reviewed according to Science X's editorial process, ensuring credibility However, it is a news article and may not provide the depth of scientific detail found in primary research articles \n**Significance**: The focus on enabling self-adaptation in artificial organelles is significant for developing systems that can sustain ATP production under varying conditions, similar to natural mitochondria \n### 3 Stem Cell-Derived Mitochondrial Transplantation\n**Source URL**: [Cell & Bioscience](https://cellandbioscience.biomedcentral.com/articles/10.1186/s13578-022-00805-7)\n\n**Relevance**: This source explores the concept of mitochondrial transplantation, which could be a step towards understanding how to maintain mitochondrial function outside of the cell \n**Reliability**: Published in a peer-reviewed journal, this article provides a reliable account of current research in mitochondrial transplantation and its potential applications \n**Significance**: The techniques discussed for preserving and transferring mitochondria could inform methods for creating ex vivo environments that support mitochondrial ATP production \n### 4 Photosynthetic Artificial Organelles in Artificial Cells\n**Source URL**: [Nature Communications](https://www.nature.com/articles/s41467-019-09147-4)\n\n**Relevance**: This research demonstrates the construction of an artificial cell system that includes a biomimetic artificial organelle capable of ATP production The system uses ATP synthase and bacteriorhodopsin to generate ATP, mimicking natural energy conversion processes \n**Reliability**: As a peer-reviewed article in a reputable journal, this source is highly reliable and provides experimental evidence of ATP production in an artificial environment \n**Significance**: The successful synthesis of ATP in this artificial system is a significant step towards replicating mitochondrial functions outside of the cell It provides a model for how essential cellular conditions for ATP production can be recreated \n### 5 Mitochondria Function and Dynamics\n**Source URL**: [Boundless Biology](https://bio.libretexts.org/Bookshelves/Introductory_and_General_Biology/Book:_General_Biology_(Boundless)/04:_Cell_Structure/4.09:_Eukaryotic_Cells_-_Mitochondria)\n\n**Relevance**: This educational resource provides foundational knowledge on mitochondrial function, including ATP production and the importance of mitochondrial dynamics \n**Reliability**: The source is part of an open educational resource, which may not have the same level of scrutiny as peer-reviewed literature However, it is useful for understanding basic concepts \n**Significance**: Understanding the fundamental role of mitochondria in energy production is essential for any attempt to replicate these processes ex vivo This source provides the necessary background information \n### 6 Mitochondrial Dynamics and Cellular Stress Responses\n**Source URL**: [Nature Cell Biology](https://www.nature.com/articles/s41556-018-0139-7)\n\n**Relevance**: This source discusses the role of mitochondrial dynamics in cellular stress responses and how these processes can be manipulated for therapeutic purposes \n**Reliability**: Published in a high-impact, peer-reviewed journal, this source is highly reliable and provides insights into the latest research on mitochondrial function \n**Significance**: Understanding how mitochondria respond to stress and maintain energy production is crucial for creating conditions that support mitochondrial functions outside of the cell \n### 7 Strategies for Targeting Mitochondrial Dynamics\n**Source URL**: [Molecular Cell](https://www.nature.com/articles/s41392-023-01547-9)\n\n**Relevance**: This article provides strategies for targeting mitochondrial dynamics, which could be applied to maintain or replicate mitochondrial functions in artificial environments \n**Reliability**: As a peer-reviewed article, this source is reliable and offers a comprehensive overview of current approaches to modulating mitochondrial dynamics \n**Significance**: The therapeutic strategies discussed could inform the development of systems that mimic the essential conditions for mitochondrial ATP production outside of the cellular environment", "summary": "Revised Summary (Iteration 3): **SPR: Bibliography Recommendation Report**\n\n- Research Question: How can we create or mimic the essential cellular conditions that support mitochondrial functions, such as ATP production, outside of the cellular environment?\n- Summary: This report analyzes several sources that contribute to our understanding of mitochondrial ATP production and the potential for its replication ex vivo. It explores a thermodynamically consistent model for ATP production in mitochondria, the challenges and future directions in creating artificial cells with biologically realistic energy-generation methods, the concept of mitochondrial transplantation, the construction of an artificial cell system that includes a biomimetic artificial organelle capable of ATP production, foundational knowledge on mitochondrial function, the role of mitochondrial dynamics in cellular stress responses, and strategies for targeting mitochondrial dynamics. These sources provide insights into the conditions necessary for ATP synthesis and the development of systems that replicate mitochondrial functions outside of the cellular environment. Synthetic biology enables the manipulation of cellular processes for therapeutic purposes, and disease modeling can be achieved through the use of stem cell-derived mitochondrial transplantation. Photosynthetic artificial organelles have the potential to replicate mitochondrial functions in artificial environments, and understanding the conditions necessary for ATP synthesis outside of a cellular environment is crucial for sustainable chemical energy conversion. Self-adaptation allows for the maintenance of a stable ATP supply in changing environments, and successful synthesis of ATP in an artificial system requires the replication of essential mitochondrial functions. Preprints on bioRxiv and articles in journals like Nature Communications provide valuable insights into mitochondrial ATP production, while educational resources like Boundless Biology and Nature Cell Biology can aid in understanding basic concepts related to mitochondrial ATP production. Therapeutic interventions targeting mitochondrial dynamics and cellular stress responses can improve disease outcomes, and Nature Communications and Cell & Bioscience are reputable sources for research on artificial cells and mitochondrial ATP production. Adenosine triphosphate (ATP) is a crucial molecule in biological systems and is necessary for various cellular functions. Synthetic biology explores the use of ATP for therapeutic interventions, while preprints provide early insights into scientific research. A thermodynamic model can predict reaction rate constants in ATP synthesis and offers valuable information on the conditions necessary for ATP production. Factors such as membrane potential, pH, and substrate concentrations play a role in ATP production and need to be considered in ex vivo replication. Self-adaptation allows ATP synthesis to adjust to changing environments, ensuring a stable ATP supply. Stem cells can be manipulated to replicate mitochondrial functions, offering potential therapeutic applications. Photosynthetic artificial organelles mimic ATP production using ATP synthase and bacteriorhodopsin, providing a model for ex vivo replication. Understanding and replicating mitochondrial functions is important for therapeutic strategies, and successful synthesis of ATP in artificial systems can be manipulated for therapeutic use. Essential conditions for mitochondrial ATP production outside of cellular environments are being studied to guide the development of ex vivo systems. Phys.org and Molecular Cell are sources for research on mitochondrial ATP production, providing valuable insights into the field. Artificial cells provide a model for studying cellular environments and diseases, aiding in disease modeling and therapeutic interventions. Stem cell-derived mitochondrial transplantation is a potential therapeutic approach that can be used to maintain mitochondrial function outside of the cell. Mitochondrial dynamics and cellular stress responses play important roles in disease modeling and can be targeted for therapeutic purposes. Strategies for targeting mitochondrial dynamics offer potential treatments for various diseases.", "clean_entities": ["ATP", "mitochondria", "adenosine triphosphate", "biological systems", "synthetic biology", "disease modeling", "therapeutic interventions", "preprint", "peer review", "thermodynamic model", "reaction rate constants", "membrane potential", "pH", "substrate concentrations", "artificial organelles", "self-adaptation", "artificial cells", "stem cells", "mitochondrial transplantation", "photosynthetic artificial organelles", "ATP synthase", "bacteriorhodopsin", "educational resource", "mitochondrial dynamics", "cellular stress responses", "therapeutic purposes", "cellular environment", "molecular cell", "mitochondrial ATP production", "cellular environment", "ATP synthesis", "thermodynamically consistent model", "artificial organelles", "sustainable chemical energy conversion", "self-adaptation", "stem cell-derived mitochondrial transplantation", "photosynthetic artificial organelles", "ATP synthase", "bacteriorhodopsin", "mitochondrial dynamics", "cellular stress responses", "therapeutic strategies", "targeting mitochondrial dynamics", "replicate mitochondrial functions outside of the cellular environment", "understanding and replicating mitochondrial functions", "conditions necessary for ATP synthesis outside of a cellular environment", "replicate mitochondrial ATP production ex vivo", "challenges and future directions in creating artificial cells", "self-adaptation in changing environments", "maintain a stable ATP supply", "mitochondrial transplantation", "construction of an artificial cell system", "biomimetic artificial organelle capable of ATP production", "successful synthesis of ATP in this artificial system", "foundational knowledge on mitochondrial function", "understanding basic concepts", "role of mitochondrial dynamics in cellular stress responses", "manipulated for therapeutic purposes", "strategies for targeting mitochondrial dynamics", "maintain or replicate mitochondrial functions in artificial environments", "essential conditions for mitochondrial ATP production outside of the cellular environment", "bioRxiv", "Phys.org", "Cell & Bioscience", "Nature Communications", "Boundless Biology", "Nature Cell Biology", "Molecular Cell", "Mitochondrial ATP production", "Artificial cells", "Cellular environment", "Synthetic biology", "Disease modeling", "Therapeutic interventions", "Thermodynamic model", "Self-adaptation", "Stem cell-derived mitochondrial transplantation", "Photosynthetic artificial organelles", "Mitochondrial dynamics", "Cellular stress responses", "Therapeutic strategies", "Targeting mitochondrial dynamics"], "dirty_entities": ["Entities:", "", "", "Keywords:", "", "", "Phrases:", "", "which could be a step towards understanding how to maintain mitochondrial function outside of the cell", "", "References:", "", "", "Abstract Concepts:", ""], "references": "", "topics": [{"topic": "Mitochondrial ATP production and replication ex vivo", "justification": "The research question and summary focus on understanding and replicating mitochondrial ATP production outside of the cellular environment."}, {"topic": "Challenges and future directions in creating artificial cells with biologically realistic energy-generation methods", "justification": "The summary mentions the challenges and future directions in creating artificial cells with energy-generation methods that mimic biological processes."}, {"topic": "Mitochondrial transplantation and its potential for disease modeling and therapeutic purposes", "justification": "The summary discusses the concept of mitochondrial transplantation and its potential applications in disease modeling and therapeutic interventions."}, {"topic": "Artificial cell systems and biomimetic artificial organelles capable of ATP production", "justification": "The summary mentions the construction of an artificial cell system that includes a biomimetic artificial organelle capable of ATP production."}, {"topic": "Foundational knowledge on mitochondrial function and its role in cellular stress responses", "justification": "The summary mentions foundational knowledge on mitochondrial function and its role in cellular stress responses, which is relevant to understanding ATP production."}, {"topic": "Strategies for targeting mitochondrial dynamics and their potential therapeutic applications", "justification": "The summary discusses strategies for targeting mitochondrial dynamics and their potential applications in therapeutic interventions."}, {"topic": "Conditions necessary for ATP synthesis outside of a cellular environment", "justification": "The summary emphasizes the importance of understanding the conditions necessary for ATP synthesis outside of a cellular environment for sustainable chemical energy conversion."}, {"topic": "Synthetic biology and its exploration of ATP for therapeutic interventions", "justification": "The summary mentions synthetic biology's exploration of ATP for therapeutic interventions."}, {"topic": "Preprints and scientific articles as valuable sources of insights into mitochondrial ATP production", "justification": "The summary highlights the value of preprints and scientific articles in providing insights into mitochondrial ATP production."}, {"topic": "Stem cell-derived mitochondrial transplantation as a potential therapeutic approach", "justification": "The summary mentions stem cell-derived mitochondrial transplantation as a potential therapeutic approach for maintaining mitochondrial function outside of the cell."}, {"topic": "Photosynthetic artificial organelles and their potential for replicating mitochondrial functions in artificial environments", "justification": "The summary mentions photosynthetic artificial organelles as a potential model for replicating mitochondrial functions in artificial environments."}, {"topic": "Therapeutic interventions targeting mitochondrial dynamics and cellular stress responses", "justification": "The summary discusses therapeutic interventions targeting mitochondrial dynamics and cellular stress responses for improving disease outcomes."}, {"topic": "Phys.org and Molecular Cell as sources for research on mitochondrial ATP production", "justification": "The summary mentions Phys.org and Molecular Cell as sources for research on mitochondrial ATP production."}, {"topic": "Artificial cells as a model for studying cellular environments and diseases", "justification": "The summary highlights the use of artificial cells as a model for studying cellular environments and diseases, which is relevant to understanding ATP production."}, {"topic": "Strategies for targeting mitochondrial dynamics for potential disease treatments", "justification": "The summary mentions strategies for targeting mitochondrial dynamics as potential treatments for various diseases."}], "hypothetical_questions": [{"question_type": "Content-Based Question", "question": "How can we create or mimic the essential cellular conditions that support mitochondrial functions, such as ATP production, outside of the cellular environment?"}, {"question_type": "Analytical Question", "question": "What are the challenges and future directions in creating artificial cells with biologically realistic energy-generation methods?"}, {"question_type": "Creative/Scenario-Based Question", "question": "Imagine a scenario where a biomimetic artificial organelle capable of ATP production is successfully constructed. How could this technology be applied in the field of medicine?"}, {"question_type": "Contextual/Relational Question", "question": "How do mitochondrial dynamics and cellular stress responses contribute to disease modeling, and how can they be targeted for therapeutic purposes?"}, {"question_type": "User-Interactive Question", "question": "Considering the sources mentioned in the summary (such as Nature Communications and Boundless Biology), how would you approach designing an experiment to replicate mitochondrial ATP production outside of the cellular environment?"}], "knowledge_triplets": [{"subject": "mitochondria", "relationship": "responsible for", "target": "production of adenosine triphosphate"}, {"subject": "mitochondrial ATP production", "relationship": "necessary for", "target": "understanding the conditions"}, {"subject": "mitochondrial ATP production", "relationship": "link to", "target": "mitochondrial morphology"}, {"subject": "mitochondrial ATP production", "relationship": "guide the design of", "target": "artificial systems"}, {"subject": "artificial cells", "relationship": "importance of", "target": "self-adaptation in changing environments"}, {"subject": "artificial organelles", "relationship": "significant for", "target": "sustaining ATP production"}, {"subject": "mitochondrial transplantation", "relationship": "potential for", "target": "maintaining mitochondrial function"}, {"subject": "artificial cell system", "relationship": "capable of", "target": "ATP production"}, {"subject": "ATP production", "relationship": "essential for", "target": "replicating mitochondrial functions"}, {"subject": "mitochondrial function", "relationship": "foundational knowledge on", "target": "ATP production"}, {"subject": "mitochondrial dynamics", "relationship": "role in", "target": "cellular stress responses"}, {"subject": "mitochondrial dynamics", "relationship": "manipulated for", "target": "therapeutic purposes"}, {"subject": "mitochondrial dynamics", "relationship": "targeted for", "target": "maintaining or replicating mitochondrial functions"}, {"subject": "mitochondrial ATP production", "relationship": "essential conditions for", "target": "outside of the cellular environment"}, {"subject": "mitochondria", "relationship": "responsible for", "target": "production of adenosine triphosphate (ATP"}, {"subject": "mitochondrial ATP production", "relationship": "crucial for", "target": "understanding the conditions necessary for ATP synthesis outside of a cellular environment"}, {"subject": "mitochondrial ATP production", "relationship": "link to", "target": "mitochondrial morphology"}, {"subject": "artificial cells", "relationship": "biologically realistic energy-generation methods", "target": "maintain a stable ATP supply"}, {"subject": "artificial organelles", "relationship": "self-adaptation", "target": "maintain a stable ATP supply"}, {"subject": "mitochondrial transplantation", "relationship": "step towards", "target": "understanding how to maintain mitochondrial function outside of the cell"}, {"subject": "mitochondrial transplantation", "relationship": "preserve and transfer", "target": "mitochondria"}, {"subject": "artificial cell system", "relationship": "biomimetic artificial organelle", "target": "ATP production"}, {"subject": "ATP synthase and bacteriorhodopsin", "relationship": "generate ATP", "target": "mimicking natural energy conversion processes"}, {"subject": "mitochondrial function", "relationship": "ATP production", "target": "mitochondrial dynamics"}, {"subject": "mitochondrial dynamics", "relationship": "cellular stress responses", "target": "manipulate for therapeutic purposes"}, {"subject": "mitochondrial dynamics", "relationship": "maintain or replicate", "target": "mitochondrial functions in artificial environments"}, {"subject": "targeting mitochondrial dynamics", "relationship": "maintain or replicate", "target": "mitochondrial functions in artificial environments"}, {"subject": "targeting mitochondrial dynamics", "relationship": "comprehensive overview", "target": "current approaches to modulating mitochondrial dynamics"}, {"subject": "therapeutic strategies", "relationship": "inform the development of", "target": "systems that mimic the essential conditions for mitochondrial ATP production outside of the cellular environment"}, {"subject": "mitochondria", "relationship": "responsible for", "target": "production of adenosine triphosphate (ATP"}, {"subject": "mitochondrial ATP production", "relationship": "crucial for", "target": "understanding the conditions necessary for ATP synthesis outside of a cellular environment"}, {"subject": "mitochondrial ATP production", "relationship": "link to", "target": "mitochondrial morphology"}, {"subject": "artificial cells", "relationship": "biologically realistic energy-generation methods", "target": "maintain a stable ATP supply"}, {"subject": "artificial organelles", "relationship": "self-adaptation", "target": "maintain a stable ATP supply"}, {"subject": "mitochondrial transplantation", "relationship": "step towards", "target": "understanding how to maintain mitochondrial function outside of the cell"}, {"subject": "mitochondrial transplantation", "relationship": "preserve and transfer", "target": "mitochondria"}, {"subject": "artificial cell system", "relationship": "biomimetic artificial organelle", "target": "ATP production"}, {"subject": "ATP synthase and bacteriorhodopsin", "relationship": "generate ATP", "target": "mimicking natural energy conversion processes"}, {"subject": "mitochondrial function", "relationship": "ATP production", "target": "mitochondrial dynamics"}, {"subject": "mitochondrial dynamics", "relationship": "cellular stress responses", "target": "manipulate for therapeutic purposes"}, {"subject": "mitochondrial dynamics", "relationship": "maintain or replicate", "target": "mitochondrial functions in artificial environments"}, {"subject": "targeting mitochondrial dynamics", "relationship": "maintain or replicate", "target": "mitochondrial functions in artificial environments"}, {"subject": "targeting mitochondrial dynamics", "relationship": "comprehensive overview", "target": "current approaches to modulating mitochondrial dynamics"}, {"subject": "therapeutic strategies", "relationship": "inform the development of", "target": "systems that mimic the essential conditions for mitochondrial ATP production outside of the cellular environment"}], "timestamp": "2024-01-10T20:13:40.722313"}, {"file_id": "19bc86d438fd4d06b14a99c32595b0ad", "article": "Chunk # 1.\n\n## Conclusion\nThe sources recommended in this report collectively provide a comprehensive understanding of mitochondrial ATP production and the potential for its replication outside of the cellular environment They range from theoretical models to experimental evidence of artificial organelles capable of ATP synthesis Understanding the fundamental principles of mitochondrial function, as well as the latest research on mitochondrial dynamics and stress responses, is essential for developing methods to mimic these processes ex vivo The reliability of these sources varies, with peer-reviewed articles offering the most credible information However, all sources contribute valuable insights into the research question and should be considered for a thorough investigation into creating or mimicking essential cellular conditions that support mitochondrial functions.", "summary": "Revised Summary:\n1. Comprehensive understanding of mitochondrial ATP production and replication, including the latest research on mitochondrial dynamics and stress responses.\n2. Range of sources, from theoretical models to experimental evidence, and research on artificial organelles capable of ATP synthesis.\n3. Importance of understanding mitochondrial function for developing methods to mimic essential cellular conditions that support ATP production and replication.\n4. Peer-reviewed articles provide valuable insights into the research question, with a focus on the potential for replication outside of the cellular environment.\n5. Methods to mimic essential cellular conditions support mitochondrial functions, such as ATP production and replication, with artificial organelles created to replicate these conditions.\n6. Peer-reviewed articles explore creating and mimicking mitochondrial ATP production and replication outside of cells.\n7. Theoretical models and experimental evidence support the development of artificial organelles capable of ATP synthesis.\n8. Understanding the fundamental principles of mitochondrial function is crucial in devising methods to mimic these processes ex vivo.\n9. The reliability of sources offering information on this topic varies, with peer-reviewed articles being the most credible.\n10. This report recommends consulting these peer-reviewed sources for a comprehensive understanding of mitochondrial ATP production.", "clean_entities": ["mitochondrial ATP production", "cellular environment", "artificial organelles", "ATP synthesis", "mitochondrial function", "mitochondrial dynamics", "stress responses", "peer-reviewed articles", "understanding", "replication", "theoretical models", "experimental evidence", "methods", "research question", "creating", "mimicking", "essential cellular conditions", "support", "mitochondrial ATP production and replication outside of the cellular environment", "theoretical models to experimental evidence of artificial organelles capable of ATP synthesis", "fundamental principles of mitochondrial function", "latest research on mitochondrial dynamics and stress responses", "methods to mimic these processes ex vivo", "reliability of these sources varies", "peer-reviewed articles offering the most credible information", "valuable insights into the research question", "sources recommended in this report", "these sources", "comprehensive understanding of mitochondrial ATP production", "potential for replication outside of the cellular environment", "methods to mimic essential cellular conditions", "support mitochondrial functions"], "dirty_entities": ["Entities:", "", "Keywords:", "", "Key Phrases:", "", "References:", "", "Abstract Concepts:", "", "Final Output: mitochondrial ATP production", "cellular environment", "artificial organelles", "ATP synthesis", "mitochondrial function", "mitochondrial dynamics", "stress responses", "peer-reviewed articles", "understanding", "replication", "theoretical models", "experimental evidence", "methods", "research question", "creating", "mimicking", "essential cellular conditions", "support", "sources recommended in this report", "comprehensive understanding of mitochondrial ATP production", "potential for replication outside of the cellular environment", "methods to mimic essential cellular conditions", "support mitochondrial functions"], "references": "", "topics": [{"topic": "Mitochondrial ATP production and replication", "justification": "The summary emphasizes a comprehensive understanding of mitochondrial ATP production and replication, including the latest research on dynamics and stress responses."}, {"topic": "Research on artificial organelles for ATP synthesis", "justification": "The summary highlights the range of sources, from theoretical models to experimental evidence, and research on artificial organelles capable of ATP synthesis."}, {"topic": "Importance of understanding mitochondrial function for mimicking cellular conditions", "justification": "The summary mentions the importance of understanding mitochondrial function for developing methods to mimic essential cellular conditions that support ATP production and replication."}, {"topic": "Peer-reviewed articles as valuable insights into the research question", "justification": "The summary states that peer-reviewed articles provide valuable insights into the research question, with a focus on the potential for replication outside of the cellular environment."}, {"topic": "Methods to mimic essential cellular conditions for mitochondrial functions", "justification": "The summary discusses methods to mimic essential cellular conditions that support mitochondrial functions, such as ATP production and replication, with artificial organelles created to replicate these conditions."}, {"topic": "Creating and mimicking mitochondrial ATP production and replication outside of cells", "justification": "The summary mentions that peer-reviewed articles explore creating and mimicking mitochondrial ATP production and replication outside of cells."}, {"topic": "Theoretical models and experimental evidence for artificial organelles capable of ATP synthesis", "justification": "The summary highlights the support from theoretical models and experimental evidence for the development of artificial organelles capable of ATP synthesis."}, {"topic": "Understanding fundamental principles of mitochondrial function for devising ex vivo methods", "justification": "The summary states that understanding the fundamental principles of mitochondrial function is crucial in devising methods to mimic these processes ex vivo."}, {"topic": "Reliability of sources on mitochondrial ATP production", "justification": "The summary mentions that the reliability of sources offering information on this topic varies, with peer-reviewed articles being the most credible."}, {"topic": "Recommendation to consult peer-reviewed sources for comprehensive understanding", "justification": "The summary recommends consulting peer-reviewed sources for a comprehensive understanding of mitochondrial ATP production."}], "hypothetical_questions": [{"question_type": "Content-Based Question", "question": "How does understanding mitochondrial dynamics and stress responses contribute to our knowledge of ATP production and replication?"}, {"question_type": "Analytical Question", "question": "What are the different sources of evidence, including theoretical models and experimental research, that support the understanding of mitochondrial ATP production and replication?"}, {"question_type": "Creative/Scenario-Based Question", "question": "Imagine a scenario where artificial organelles capable of ATP synthesis are successfully developed. How could this impact the field of cellular research and the development of new therapies?"}, {"question_type": "Contextual/Relational Question", "question": "How does the understanding of mitochondrial function and the development of methods to mimic cellular conditions relate to the goal of replicating ATP production outside of the cellular environment?"}, {"question_type": "User-Interactive Question", "question": "How would you approach designing an experiment to study mitochondrial ATP production and replication using artificial organelles?"}], "knowledge_triplets": [{"subject": "mitochondrial ATP production", "relationship": "is essential for", "target": "developing methods to mimic these processes ex vivo"}, {"subject": "mitochondrial ATP production", "relationship": "is essential for", "target": "creating or mimicking essential cellular conditions that support mitochondrial functions"}, {"subject": "mitochondrial ATP production", "relationship": "is essential for", "target": "creating or mimicking essential cellular conditions"}, {"subject": "mitochondrial ATP production", "relationship": "is essential for", "target": "support mitochondrial functions"}, {"subject": "mitochondrial ATP production", "relationship": "is essential for", "target": "methods to mimic these processes ex vivo"}, {"subject": "mitochondrial ATP production", "relationship": "is essential for", "target": "methods to mimic essential cellular conditions"}, {"subject": "mitochondrial ATP production", "relationship": "is essential for", "target": "methods to mimic essential cellular conditions that support mitochondrial functions"}, {"subject": "mitochondrial ATP production", "relationship": "is essential for", "target": "methods to mimic these processes ex vivo"}, {"subject": "mitochondrial ATP production", "relationship": "is essential for", "target": "creating or mimicking essential cellular conditions that support mitochondrial functions"}, {"subject": "mitochondrial ATP production", "relationship": "is essential for", "target": "creating or mimicking essential cellular conditions"}, {"subject": "mitochondrial ATP production", "relationship": "is essential for", "target": "support mitochondrial functions"}, {"subject": "mitochondrial ATP production", "relationship": "is essential for", "target": "methods to mimic these processes ex vivo"}, {"subject": "mitochondrial ATP production", "relationship": "is essential for", "target": "methods to mimic essential cellular conditions"}, {"subject": "mitochondrial ATP production", "relationship": "is essential for", "target": "methods to mimic essential cellular conditions that support mitochondrial functions"}, {"subject": "mitochondrial ATP production", "relationship": "is essential for", "target": "methods to mimic these processes ex vivo"}, {"subject": "mitochondrial ATP production", "relationship": "is essential for", "target": "creating or mimicking essential cellular conditions that support mitochondrial functions"}, {"subject": "mitochondrial ATP production", "relationship": "is essential for", "target": "creating or mimicking essential cellular conditions"}, {"subject": "mitochondrial ATP production", "relationship": "is essential for", "target": "support mitochondrial functions"}, {"subject": "mitochondrial ATP production", "relationship": "is essential for", "target": "methods to mimic these processes ex vivo"}, {"subject": "mitochondrial ATP production", "relationship": "is essential for", "target": "methods to mimic essential cellular conditions"}, {"subject": "mitochondrial ATP production", "relationship": "is essential for", "target": "methods to mimic essential cellular conditions that support mitochondrial functions"}, {"subject": "mitochondrial ATP production", "relationship": "is essential for", "target": "methods to mimic these processes ex vivo"}, {"subject": "mitochondrial ATP production", "relationship": "is essential for", "target": "creating or mimicking essential cellular conditions that support mitochondrial functions"}, {"subject": "mitochondrial ATP production", "relationship": "is essential for", "target": "creating or mimicking essential cellular conditions"}, {"subject": "mitochondrial ATP production", "relationship": "is essential for", "target": "support mitochondrial functions"}, {"subject": "mitochondrial ATP production", "relationship": "is essential for", "target": "methods to mimic these processes ex vivo"}, {"subject": "mitochondrial ATP production", "relationship": "is essential for", "target": "methods to mimic essential cellular conditions"}, {"subject": "mitochondrial ATP production", "relationship": "is essential for", "target": "methods to mimic essential cellular conditions that support mitochondrial functions"}, {"subject": "mitochondrial ATP production", "relationship": "is essential for", "target": "methods to mimic these processes ex vivo"}, {"subject": "mitochondrial ATP production", "relationship": "is essential for", "target": "creating or mimicking essential cellular conditions that support mitochondrial functions"}, {"subject": "mitochondrial ATP production", "relationship": "comprehensive understanding of", "target": "mitochondrial ATP production"}, {"subject": "mitochondrial ATP production", "relationship": "potential for replication outside of", "target": "cellular environment"}, {"subject": "mitochondrial ATP production", "relationship": "methods to mimic essential cellular conditions", "target": "support mitochondrial functions"}, {"subject": "mitochondrial ATP production", "relationship": "is essential for", "target": "developing methods to mimic these processes ex vivo"}, {"subject": "mitochondrial ATP production", "relationship": "is essential for", "target": "creating or mimicking essential cellular conditions that support mitochondrial functions"}, {"subject": "mitochondrial ATP production", "relationship": "is essential for", "target": "creating or mimicking essential cellular conditions"}, {"subject": "mitochondrial ATP production", "relationship": "is essential for", "target": "support mitochondrial functions"}, {"subject": "mitochondrial ATP production", "relationship": "is essential for", "target": "methods to mimic these processes ex vivo"}, {"subject": "mitochondrial ATP production", "relationship": "is essential for", "target": "methods to mimic essential cellular conditions"}, {"subject": "mitochondrial ATP production", "relationship": "is essential for", "target": "methods to mimic essential cellular conditions that support mitochondrial functions"}, {"subject": "mitochondrial ATP production", "relationship": "is essential for", "target": "creating or mimicking essential cellular conditions that support mitochondrial functions"}, {"subject": "mitochondrial ATP production", "relationship": "is essential for", "target": "creating or mimicking essential cellular conditions"}, {"subject": "mitochondrial ATP production", "relationship": "is essential for", "target": "support mitochondrial functions"}, {"subject": "mitochondrial ATP production", "relationship": "is essential for", "target": "methods to mimic these processes ex vivo"}, {"subject": "mitochondrial ATP production", "relationship": "is essential for", "target": "methods to mimic essential cellular conditions"}, {"subject": "mitochondrial ATP production", "relationship": "is essential for", "target": "methods to mimic essential cellular conditions that support mitochondrial functions"}, {"subject": "mitochondrial ATP production", "relationship": "is essential for", "target": "methods to mimic these processes ex vivo"}, {"subject": "mitochondrial ATP production", "relationship": "is essential for", "target": "creating or mimicking essential cellular conditions that support mitochondrial functions"}, {"subject": "mitochondrial ATP production", "relationship": "is essential for", "target": "creating or mimicking essential cellular conditions"}, {"subject": "mitochondrial ATP production", "relationship": "is essential for", "target": "support mitochondrial functions"}, {"subject": "mitochondrial ATP production", "relationship": "is essential for", "target": "methods to mimic these processes ex vivo"}, {"subject": "mitochondrial ATP production", "relationship": "is essential for", "target": "methods to mimic essential cellular conditions"}, {"subject": "mitochondrial ATP production", "relationship": "is essential for", "target": "methods to mimic essential cellular conditions that support mitochondrial functions"}, {"subject": "mitochondrial ATP production", "relationship": "is essential for", "target": "methods to mimic these processes ex vivo"}, {"subject": "mitochondrial ATP production", "relationship": "is essential for", "target": "creating or mimicking essential cellular conditions that support mitochondrial functions"}, {"subject": "mitochondrial ATP production", "relationship": "is essential for", "target": "creating or mimicking essential cellular conditions"}, {"subject": "mitochondrial ATP production", "relationship": "is essential for", "target": "support mitochondrial functions"}, {"subject": "mitochondrial ATP production", "relationship": "is essential for", "target": "methods to mimic these processes ex vivo"}, {"subject": "mitochondrial ATP production", "relationship": "is essential for", "target": "methods to mimic essential cellular conditions"}, {"subject": "mitochondrial ATP production", "relationship": "is essential for", "target": "methods to mimic essential cellular conditions that support mitochondrial functions"}, {"subject": "mitochondrial ATP production", "relationship": "is essential for", "target": "methods to mimic these processes ex vivo"}, {"subject": "mitochondrial ATP production", "relationship": "is essential for", "target": "creating or mimicking essential cellular conditions that support mitochondrial functions"}, {"subject": "mitochondrial ATP production", "relationship": "is essential for", "target": "creating or mimicking essential cellular conditions"}, {"subject": "mitochondrial ATP production", "relationship": "comprehensive understanding of", "target": "mitochondrial ATP production"}, {"subject": "mitochondrial ATP production", "relationship": "potential for replication outside of", "target": "cellular environment"}, {"subject": "mitochondrial ATP production", "relationship": "methods to mimic essential cellular conditions", "target": "support mitochondrial functions"}], "timestamp": "2024-01-10T20:14:41.234332"}]