[{"file_id": "6a6833e6bf9b4723b80b992cfd1c3c09", "article": "Chunk # 0.\n# Bibliography Recommendation Report\n\n## Research Question\nWhat genetic modifications could be introduced to mitochondria to enhance their autonomy from nuclear-encoded proteins and functions \n## Introduction\nMitochondria are unique organelles with their own genome, mitochondrial DNA (mtDNA), which encodes for a small number of proteins essential for mitochondrial function However, the majority of mitochondrial proteins are encoded by nuclear DNA, necessitating a tight coordination between the nuclear and mitochondrial genomes Enhancing mitochondrial autonomy could potentially lead to novel therapeutic strategies for mitochondrial diseases and a better understanding of mitochondrial biology This report analyzes several scientific sources that contribute to the understanding of potential genetic modifications to mitochondria to enhance their autonomy \n## Source Analysis\n\n### Source 1: Nature Reviews Genetics\n**Title:** The potential of mitochondrial genome engineering\n**URL:** [Nature Reviews Genetics](https://www.nature.com/articles/s41576-021-00432-x)\n\n**Relevance:** This article discusses recent developments in mitochondrial genome engineering, which is directly relevant to the research question It highlights the challenges and potential of using genome editing technologies, such as programmable nucleases and base editors, for the treatment of hereditary mitochondrial diseases \n**Reliability:** Published in a highly reputable journal, this review article provides a comprehensive overview of the field, making it a reliable source The authors are experts in the field, and the article has been cited by other researchers, indicating its impact on the scientific community \n**Significance:** The article provides insights into the unique genetic control of mitochondria by both nuclear DNA and mtDNA It also discusses the implications of mtDNA mutations and the resistance of mammalian mtDNA to genetic manipulation This information is crucial for understanding how genetic modifications could enhance mitochondrial autonomy \n### Source 2: PubMed Central\n**Title:** MITOCHONDRIAL GENOME ENGINEERING COMING-OF-AGE\n**URL:** [PubMed Central](https://www.ncbi.nlm.nih.gov/pmc/articles/PMC9283244/)\n\n**Relevance:** This source provides an overview of the challenges and advances in mitochondrial genome engineering, including the development of specific nucleases and base editors for mtDNA editing It is relevant to the research question as it discusses the tools that could potentially be used to modify the mitochondrial genome to increase autonomy \n**Reliability:** The article is available on PubMed Central, a free full-text archive of biomedical and life sciences journal literature It is peer-reviewed and provides detailed information on the subject, making it a reliable source for researchers \n**Significance:** The source discusses the limitations of mtDNA recombination and the use of protein-only gene editing platforms, which are major advances in the ability to precisely alter mtDNA in animal cells This information is significant for understanding the current state of mitochondrial genome engineering and its potential for enhancing mitochondrial autonomy \n### Source 3: Scientific Reports\n**Title:** Generation of somatic mitochondrial DNA-replaced cells for mitochondrial dysfunction treatment\n**URL:** [Scientific Reports](https://www.nature.com/articles/s41598-021-90316-1)\n\n**Relevance:** This article describes a protocol for mitochondrial DNA replacement in human fibroblasts, which is relevant to the research question as it demonstrates a method to alter mitochondrial genomes \n**Reliability:** Published in Scientific Reports, an open-access journal known for rigorous peer-review, the article provides experimental evidence and data that support its findings, enhancing its reliability \n**Significance:** The protocol offers a potential treatment for mitochondrial diseases by replacing mutated mtDNA with healthy mtDNA This approach could be a step towards enhancing mitochondrial autonomy by allowing mitochondria to function properly without the influence of nuclear-encoded mutations \n### Source 4: Journal of Cell Biology\n**Title:** Mitochondrial nucleoids maintain genetic autonomy but allow for functional complementation\n**URL:** [Journal of Cell Biology](https://rupress.org/jcb/article/181/7/1117/45294/Mitochondrial-nucleoids-maintain-genetic-autonomy)\n\n**Relevance:** This source discusses the concept of mitochondrial nucleoids and their role in maintaining genetic autonomy It is relevant to the research question as it provides a molecular mechanism that could be targeted for enhancing mitochondrial autonomy \n**Reliability:** The Journal of Cell Biology is a reputable journal, and the article is distributed under a Creative Commons License, ensuring its accessibility and reliability The research presented is peer-reviewed and contributes to the understanding of mitochondrial inheritance \n**Significance:** The article's focus on the genetic autonomy of mitochondrial nucleoids and their ability for functional complementation is significant for understanding how mitochondria can maintain autonomy while still interacting with nuclear-encoded functions \n### Source 5: Nature Communications\n**Title:** Mitochondrial epigenomics\n**URL:** [Nature Communications](https://www.ncbi.nlm.nih.gov/pmc/articles/PMC7017415/)\n\n**Relevance:** This source explores the epigenomic regulation of mitochondrial function and its interplay with nuclear DNA It is relevant to the research question as it discusses how modifications in mitochondrial gene expression can lead to pathologies and potentially how autonomy could be enhanced \n**Reliability:** As a publication in Nature Communications, this article is part of a highly respected journal family The peer-reviewed nature of the article and the detailed review of mitochondrial epigenomics make it a reliable source \n**Significance:** The article provides a comprehensive review of mitochondrial gene expression mechanisms and their regulation under different cellular contexts, including stress conditions This knowledge is crucial for identifying potential genetic modifications that could enhance mitochondrial autonomy", "summary": "Summary: **SPR: Bibliography Recommendation Report**\n\n1. Recent developments in mitochondrial genome engineering, including the use of nucleases and base editors, show promise for enhancing mitochondrial autonomy and treating hereditary mitochondrial diseases. Genome editing technologies have the potential to treat hereditary mitochondrial diseases. Nucleases and base editors are specific tools used for modifying the mitochondrial genome. (Source: Nature Reviews Genetics, PubMed Central)\n2. A protocol for mitochondrial DNA replacement offers a potential treatment for mitochondrial diseases by replacing mutated mtDNA with healthy mtDNA, increasing mitochondrial autonomy. Protein-only gene editing platforms offer a novel approach to alter mitochondrial DNA. Animal cells and human fibroblasts are commonly used in mitochondrial genome engineering research. (Source: Scientific Reports)\n3. Mitochondrial nucleoids maintain genetic autonomy while allowing for functional complementation, contributing to our understanding of mitochondrial autonomy. (Source: Journal of Cell Biology)\n4. Mitochondrial epigenomics explores the interplay between mitochondrial and nuclear DNA, providing insights into potential enhancements to mitochondrial autonomy and addressing pathologies in different cellular contexts and stress conditions. Understanding the molecular mechanisms and epigenomic regulation of mitochondrial gene expression is crucial for developing therapeutic strategies. Mitochondrial diseases and pathologies can be studied in various cellular contexts and stress conditions. (Source: Nature Communications)\n5. Coordination between nuclear DNA and mitochondrial DNA is essential for maintaining mitochondrial autonomy. Advances in mitochondrial genome engineering present both challenges and opportunities for treating mitochondrial diseases. Scientific sources, such as Nature Reviews Genetics and PubMed Central, provide valuable insights into mitochondrial biology and genome engineering. (Source: Nature Reviews Genetics, PubMed Central)\n\nEntities: Mitochondrial DNA (mtDNA), hereditary mitochondrial diseases, genome editing technologies, nucleases, base editors, mtDNA mutations, protein-only gene editing platforms, mtDNA recombination, mitochondrial DNA replacement, molecular mechanisms, epigenomic regulation, cellular contexts, stress conditions, genome engineering, coordination between mitochondrial and nuclear DNA, mitochondrial biology, Nature Reviews Genetics, PubMed Central, Scientific Reports, Journal of Cell Biology, Nature Communications, animal cells, human fibroblasts, genetic autonomy, mitochondrial nucleoids, functional complementation.", "clean_entities": ["Mitochondria", "Mitochondrial DNA (mtDNA)", "Genome editing technologies", "Hereditary mitochondrial diseases", "Nucleases", "Base editors", "mtDNA mutations", "mtDNA recombination", "Protein-only gene editing platforms", "Animal cells", "Mitochondrial DNA replacement", "Human fibroblasts", "Mitochondrial diseases", "Mitochondrial nucleoids", "Genetic autonomy", "Molecular mechanism", "Mitochondrial epigenomics", "Epigenomic regulation", "Mitochondrial gene expression", "Pathologies", "Cellular contexts", "Stress conditions", "Genetic modifications", "Autonomy", "Enhance", "Mitochondrial function", "Therapeutic strategies", "Understanding", "Genome engineering", "Mitochondrial genome", "Coordination", "Mitochondrial biology", "Scientific sources", "Mitochondrial diseases", "Mitochondrial genome engineering", "Programmable nucleases", "Base editors", "Treatment", "Challenges", "Advances", "mtDNA editing", "mtDNA recombination", "Protein-only gene editing", "Animal cells", "Somatic mitochondrial DNA replacement", "Human fibroblasts", "Molecular mechanism", "Functional complementation", "Epigenomic regulation", "Nuclear DNA", "Mitochondrial gene expression", "Pathologies", "Cellular contexts", "Stress conditions", "Genetic modifications to mitochondria", "Enhance their autonomy", "Nuclear-encoded proteins and functions", "Mitochondrial DNA (mtDNA)", "Mitochondrial proteins", "Tight coordination", "Mitochondrial autonomy", "Novel therapeutic strategies", "Understanding of mitochondrial biology", "Recent developments in mitochondrial genome engineering", "Genome editing technologies", "Programmable nucleases", "Base editors", "Treatment of hereditary mitochondrial diseases", "Challenges and advances in mitochondrial genome engineering", "Specific nucleases and base editors", "Modify the mitochondrial genome", "Increase autonomy", "Limitations of mtDNA recombination", "Protein-only gene editing platforms", "Precisely alter mtDNA", "Mitochondrial DNA replacement", "Potential treatment for mitochondrial diseases", "Replace mutated mtDNA with healthy mtDNA", "Enhancing mitochondrial autonomy", "Molecular mechanism", "Mitochondrial nucleoids", "Genetic autonomy of mitochondrial nucleoids", "Functional complementation", "Mitochondrial epigenomics", "Epigenomic regulation of mitochondrial function", "Interplay with nuclear DNA", "Modifications in mitochondrial gene expression", "Pathologies", "Enhancing autonomy", "Nature Reviews Genetics: [Nature Reviews Genetics](https://www.nature.com/articles/s41576-021-00432-x)", "PubMed Central: [PubMed Central](https://www.ncbi.nlm.nih.gov/pmc/articles/PMC9283244/)", "Scientific Reports: [Scientific Reports](https://www.nature.com/articles/s41598-021-90316-1)", "Journal of Cell Biology: [Journal of Cell Biology](https://rupress.org/jcb/article/181/7/1117/45294/Mitochondrial-nucleoids-maintain-genetic-autonomy)", "Nature Communications: [Nature Communications](https://www.ncbi.nlm.nih.gov/pmc/articles/PMC7017415/)", "Mitochondrial genome engineering", "Mitochondrial diseases", "Genetic modifications", "Autonomy enhancement", "Genome editing technologies", "Molecular mechanisms", "Epigenomic regulation", "Pathologies", "Cellular contexts", "Stress conditions"], "dirty_entities": ["Entities:", "", "Keywords:", "", "Phrases:", "", "References:", "", "Concepts:", "", "**Final Output:**", "Entities: Mitochondria", "Mitochondrial DNA (mtDNA)", "Genome editing technologies", "Hereditary mitochondrial diseases", "Nucleases", "Base editors", "mtDNA mutations", "mtDNA recombination", "Protein-only gene editing platforms", "Animal cells", "Mitochondrial DNA replacement", "Human fibroblasts", "Mitochondrial diseases", "Mitochondrial nucleoids", "Genetic autonomy", "Molecular mechanism", "Mitochondrial epigenomics", "Epigenomic regulation", "Mitochondrial gene expression", "Pathologies", "Cellular contexts", "Stress conditions", "", "Keywords: Genetic modifications", "Autonomy", "Enhance", "Mitochondrial function", "Therapeutic strategies", "Understanding", "Genome engineering", "Mitochondrial genome", "Coordination", "Mitochondrial biology", "Scientific sources", "Programmable nucleases", "Base editors", "Treatment", "Challenges", "Advances", "mtDNA editing", "mtDNA recombination", "Protein-only gene editing", "Somatic mitochondrial DNA replacement", "Molecular mechanism", "Functional complementation", "Epigenomic regulation", "Nuclear DNA", "Pathologies", "Cellular contexts", "Stress conditions", "", "Phrases: Genetic modifications to mitochondria", "Enhance their autonomy", "Nuclear-encoded proteins and functions", "Mitochondrial DNA (mtDNA)", "Mitochondrial proteins", "Tight coordination", "Mitochondrial autonomy", "Novel therapeutic strategies", "Understanding of mitochondrial biology", "Recent developments in mitochondrial genome engineering", "Genome editing technologies", "Programmable nucleases", "Base editors", "Treatment of hereditary mitochondrial diseases", "Challenges and advances in mitochondrial genome engineering", "Specific nucleases and base editors", "Modify the mitochondrial genome", "Increase autonomy", "Limitations of mtDNA recombination", "Protein-only gene editing platforms", "Precisely alter mtDNA", "Mitochondrial DNA replacement", "Potential treatment for mitochondrial diseases", "Replace mutated mtDNA with healthy mtDNA", "Enhancing mitochondrial autonomy", "Molecular mechanism", "Mitochondrial nucleoids", "Genetic autonomy of mitochondrial nucleoids", "Functional complementation", "Mitochondrial epigenomics", "Epigenomic regulation of mitochondrial function", "Interplay with nuclear DNA", "Modifications in mitochondrial gene expression", "Pathologies", "Enhancing autonomy", "", "References: Nature Reviews Genetics", "PubMed Central", "Scientific Reports", "Journal of Cell Biology", "Nature Communications", "", "Concepts: Mitochondrial genome engineering", "Mitochondrial diseases", "Genetic modifications", "Autonomy enhancement", "Genome editing technologies", "Molecular mechanisms", "Epigenomic regulation", "Pathologies", "Cellular contexts", "Stress conditions"], "references": "", "topics": [{"topic": "Mitochondrial genome engineering for treating hereditary mitochondrial diseases", "justification": "The summary highlights recent developments in mitochondrial genome engineering and its potential for treating hereditary mitochondrial diseases. It discusses the use of nucleases, base editors, and protein-only gene editing platforms in modifying the mitochondrial genome."}, {"topic": "Mitochondrial DNA replacement as a potential treatment for mitochondrial diseases", "justification": "The summary mentions a protocol for mitochondrial DNA replacement as a potential treatment for mitochondrial diseases. It explains how this approach involves replacing mutated mtDNA with healthy mtDNA to increase mitochondrial autonomy."}, {"topic": "Role of mitochondrial nucleoids in maintaining genetic autonomy", "justification": "The summary mentions mitochondrial nucleoids and their role in maintaining genetic autonomy while allowing for functional complementation. It highlights the contribution of mitochondrial nucleoids to our understanding of mitochondrial autonomy."}, {"topic": "Mitochondrial epigenomics and its implications for enhancing mitochondrial autonomy and addressing pathologies", "justification": "The summary discusses mitochondrial epigenomics and its exploration of the interplay between mitochondrial and nuclear DNA. It emphasizes the insights provided by mitochondrial epigenomics into potential enhancements to mitochondrial autonomy and the addressing of pathologies in different cellular contexts and stress conditions."}, {"topic": "Coordination between mitochondrial and nuclear DNA for maintaining mitochondrial autonomy", "justification": "The summary emphasizes the importance of coordination between mitochondrial and nuclear DNA for maintaining mitochondrial autonomy. It mentions the challenges and opportunities presented by advances in mitochondrial genome engineering for treating mitochondrial diseases."}], "hypothetical_questions": [{"question_type": "Content-Based Question", "question": "How do recent developments in mitochondrial genome engineering, such as the use of nucleases and base editors, contribute to enhancing mitochondrial autonomy and treating hereditary mitochondrial diseases?"}, {"question_type": "Analytical Question", "question": "What are the potential challenges and opportunities presented by advances in mitochondrial genome engineering for treating mitochondrial diseases?"}, {"question_type": "Creative/Scenario-Based Question", "question": "Imagine a future where mitochondrial DNA replacement becomes a widely available treatment for mitochondrial diseases. How might this impact individuals with hereditary mitochondrial diseases and their quality of life?"}, {"question_type": "Contextual/Relational Question", "question": "How does the coordination between nuclear DNA and mitochondrial DNA contribute to maintaining mitochondrial autonomy, and what are the implications for understanding and treating mitochondrial diseases?"}, {"question_type": "User-Interactive Question", "question": "Based on the information provided, what are some potential applications of mitochondrial genome engineering in studying mitochondrial diseases and pathologies in different cellular contexts and stress conditions?"}], "knowledge_triplets": [{"subject": "Mitochondria", "relationship": "encode for", "target": "mitochondrial proteins"}, {"subject": "Mitochondria", "relationship": "necessitating", "target": "coordination between nuclear and mitochondrial genomes"}, {"subject": "Mitochondrial DNA (mtDNA)", "relationship": "encode for", "target": "small number of proteins essential for mitochondrial function"}, {"subject": "Mitochondrial DNA (mtDNA)", "relationship": "resistance to", "target": "genetic manipulation"}, {"subject": "Genome editing technologies", "relationship": "potential for", "target": "modifying the mitochondrial genome"}, {"subject": "Genome editing technologies", "relationship": "treatment of", "target": "hereditary mitochondrial diseases"}, {"subject": "Mitochondrial DNA replacement", "relationship": "potential treatment for", "target": "mitochondrial diseases"}, {"subject": "Mitochondrial DNA replacement", "relationship": "replace mutated mtDNA with", "target": "healthy mtDNA"}, {"subject": "Mitochondrial nucleoids", "relationship": "maintain", "target": "genetic autonomy"}, {"subject": "Mitochondrial nucleoids", "relationship": "allow for", "target": "functional complementation"}, {"subject": "Mitochondrial epigenomics", "relationship": "regulation of", "target": "mitochondrial function"}, {"subject": "Mitochondrial epigenomics", "relationship": "interplay with", "target": "nuclear DNA"}, {"subject": "Mitochondrial gene expression", "relationship": "modifications in", "target": "mitochondrial function"}, {"subject": "Mitochondrial gene expression", "relationship": "regulation under", "target": "different cellular contexts"}, {"subject": "Mitochondrial gene expression", "relationship": "regulation under", "target": "stress conditions"}, {"subject": "Mitochondrial gene expression", "relationship": "potential for", "target": "enhancing autonomy"}, {"subject": "Mitochondrial genome engineering", "relationship": "recent developments in", "target": "modifying the mitochondrial genome"}, {"subject": "Mitochondrial genome engineering", "relationship": "treatment of", "target": "hereditary mitochondrial diseases"}, {"subject": "Mitochondrial genome engineering", "relationship": "specific nucleases and base editors for", "target": "mtDNA editing"}, {"subject": "Mitochondrial genome engineering", "relationship": "limitations of", "target": "mtDNA recombination"}, {"subject": "Mitochondrial genome engineering", "relationship": "protein-only gene editing platforms for", "target": "precise alteration of mtDNA"}, {"subject": "Mitochondrial genome engineering", "relationship": "potential for", "target": "enhancing mitochondrial autonomy"}, {"subject": "Mitochondrial genome engineering", "relationship": "molecular mechanisms for", "target": "maintaining genetic autonomy"}, {"subject": "Autonomy enhancement", "relationship": "understanding of", "target": "mitochondrial biology"}, {"subject": "Autonomy enhancement", "relationship": "potential therapeutic strategies for", "target": "mitochondrial diseases"}, {"subject": "Mitochondria", "relationship": "encode for", "target": "small number of proteins"}, {"subject": "Mitochondria", "relationship": "encoded by", "target": "nuclear DNA"}, {"subject": "Genome editing technologies", "relationship": "potential for", "target": "modify the mitochondrial genome"}, {"subject": "Mitochondrial DNA replacement", "relationship": "potential treatment for", "target": "mitochondrial diseases"}, {"subject": "Mitochondrial nucleoids", "relationship": "maintain", "target": "genetic autonomy"}, {"subject": "Mitochondrial nucleoids", "relationship": "allow for", "target": "functional complementation"}, {"subject": "Mitochondrial gene expression", "relationship": "regulated by", "target": "epigenomic mechanisms"}, {"subject": "Mitochondrial gene expression", "relationship": "interplay with", "target": "nuclear DNA"}, {"subject": "Modifications in mitochondrial gene expression", "relationship": "can lead to", "target": "pathologies"}, {"subject": "Mitochondrial gene expression", "relationship": "regulated under", "target": "different cellular contexts"}, {"subject": "Mitochondria", "relationship": "encode for", "target": "small number of proteins"}, {"subject": "Mitochondria", "relationship": "encoded by", "target": "nuclear DNA"}, {"subject": "Genome editing technologies", "relationship": "potential for", "target": "modify the mitochondrial genome"}, {"subject": "Mitochondrial DNA replacement", "relationship": "potential treatment for", "target": "mitochondrial diseases"}, {"subject": "Mitochondrial nucleoids", "relationship": "maintain", "target": "genetic autonomy"}, {"subject": "Mitochondrial nucleoids", "relationship": "allow for", "target": "functional complementation"}, {"subject": "Mitochondrial gene expression", "relationship": "regulated by", "target": "epigenomic mechanisms"}, {"subject": "Mitochondrial gene expression", "relationship": "interplay with", "target": "nuclear DNA"}, {"subject": "Modifications in mitochondrial gene expression", "relationship": "can lead to", "target": "pathologies"}, {"subject": "Mitochondrial gene expression", "relationship": "regulated under", "target": "different cellular contexts"}], "timestamp": "2024-01-10T21:13:58.485929"}, {"file_id": "6a6833e6bf9b4723b80b992cfd1c3c09", "article": "Chunk # 1.\n\n## Conclusion\nThe sources analyzed in this report provide a broad overview of the current state of mitochondrial genome engineering and its potential for enhancing mitochondrial autonomy They offer insights into the challenges, tools, and methods available for modifying the mitochondrial genome, as well as the interplay between nuclear and mitochondrial genomes These sources are reliable and significant contributions to the field, and they collectively offer a foundation for further research into genetic modifications that could increase mitochondrial autonomy from nuclear-encoded proteins and functions.", "summary": "Mitochondrial genome engineering's current state and potential for enhancing autonomy are explored in reliable sources. Challenges, tools, and the interplay between nuclear and mitochondrial genomes are discussed, providing a foundation for future research on increasing mitochondrial autonomy.", "clean_entities": [], "dirty_entities": ["Entities: sources", "report", "state", "mitochondrial genome engineering", "potential", "mitochondrial autonomy", "insights", "challenges", "tools", "methods", "interplay", "nuclear genome", "contributions", "field", "research", "genetic modifications", "mitochondrial autonomy", "nuclear-encoded proteins", "functions.", "", "Keywords: mitochondrial genome engineering", "potential", "enhancing", "mitochondrial autonomy", "insights", "challenges", "tools", "methods", "modifying", "interplay", "nuclear genome", "reliable", "significant contributions", "field", "foundation", "research", "genetic modifications", "increase", "nuclear-encoded proteins", "functions.", "", "Key Phrases: current state", "mitochondrial genome engineering", "potential for enhancing mitochondrial autonomy", "insights into the challenges", "tools", "and methods", "modifying the mitochondrial genome", "interplay between nuclear and mitochondrial genomes", "reliable and significant contributions", "foundation for further research", "genetic modifications that could increase mitochondrial autonomy from nuclear-encoded proteins and functions.", "", "References: sources", "report", "contributions", "research.", "", "Abstract Concepts: current state", "potential", "enhancing", "mitochondrial autonomy", "insights", "challenges", "tools", "methods", "modifying", "interplay", "reliable", "significant", "foundation", "research", "genetic modifications", "increase", "nuclear-encoded proteins", "functions.", "", "Output: sources", "report", "state", "mitochondrial genome engineering", "potential", "mitochondrial autonomy", "insights", "challenges", "tools", "methods", "modifying", "interplay", "nuclear genome", "contributions", "field", "research", "genetic modifications", "nuclear-encoded proteins", "functions."], "references": "", "topics": [{"topic": "Mitochondrial genome engineering", "justification": "The summary explicitly mentions that the current state and potential of mitochondrial genome engineering are explored in reliable sources."}, {"topic": "Enhancing autonomy", "justification": "The summary mentions that mitochondrial genome engineering has the potential for enhancing autonomy."}, {"topic": "Challenges in mitochondrial genome engineering", "justification": "The summary states that challenges in mitochondrial genome engineering are discussed."}, {"topic": "Tools for mitochondrial genome engineering", "justification": "The summary mentions that tools for mitochondrial genome engineering are discussed."}, {"topic": "Interplay between nuclear and mitochondrial genomes", "justification": "The summary mentions that the interplay between nuclear and mitochondrial genomes is discussed."}, {"topic": "Foundation for future research", "justification": "The summary states that the discussion on challenges, tools, and the interplay between nuclear and mitochondrial genomes provides a foundation for future research on increasing mitochondrial autonomy."}], "hypothetical_questions": [{"question_type": "Content-Based Question", "question": "How does the current state of mitochondrial genome engineering contribute to enhancing autonomy?"}, {"question_type": "Analytical Question", "question": "What are the main challenges faced in the field of mitochondrial genome engineering, and how can they be overcome to increase mitochondrial autonomy?"}, {"question_type": "Creative/Scenario-Based Question", "question": "Imagine a future where mitochondrial genome engineering has advanced significantly. How might increased mitochondrial autonomy impact the functioning of cells and organisms?"}, {"question_type": "Contextual/Relational Question", "question": "How does the interplay between nuclear and mitochondrial genomes influence the potential for enhancing autonomy through mitochondrial genome engineering?"}, {"question_type": "User-Interactive Question", "question": "How might the concept of increasing mitochondrial autonomy through genome engineering be received by different stakeholders, such as scientists, ethicists, and the general public?"}], "knowledge_triplets": [{"subject": "mitochondrial genome engineering", "relationship": "enhancing", "target": "mitochondrial autonomy"}, {"subject": "challenges", "relationship": "modifying", "target": "mitochondrial genome"}, {"subject": "tools", "relationship": "modifying", "target": "mitochondrial genome"}, {"subject": "methods", "relationship": "modifying", "target": "mitochondrial genome"}, {"subject": "nuclear genome", "relationship": "interplay", "target": "mitochondrial genome"}, {"subject": "mitochondrial genome engineering", "relationship": "research", "target": "genetic modifications"}, {"subject": "genetic modifications", "relationship": "increasing", "target": "mitochondrial autonomy"}, {"subject": "mitochondrial genome engineering", "relationship": "enhancing", "target": "mitochondrial autonomy"}, {"subject": "mitochondrial genome engineering", "relationship": "modifying", "target": "mitochondrial genome"}, {"subject": "mitochondrial genome engineering", "relationship": "interplay between", "target": "nuclear and mitochondrial genomes"}, {"subject": "mitochondrial genome engineering", "relationship": "research into", "target": "genetic modifications"}, {"subject": "mitochondrial genome engineering", "relationship": "increase", "target": "mitochondrial autonomy"}, {"subject": "mitochondrial genome engineering", "relationship": "increase", "target": "nuclear-encoded proteins"}, {"subject": "mitochondrial genome engineering", "relationship": "increase", "target": "functions"}, {"subject": "mitochondrial genome engineering", "relationship": "increase", "target": "nuclear-encoded proteins and functions"}, {"subject": "mitochondrial genome engineering", "relationship": "enhancing", "target": "mitochondrial autonomy"}, {"subject": "mitochondrial genome engineering", "relationship": "modifying", "target": "mitochondrial genome"}, {"subject": "mitochondrial genome engineering", "relationship": "interplay between", "target": "nuclear and mitochondrial genomes"}, {"subject": "mitochondrial genome engineering", "relationship": "research into", "target": "genetic modifications"}, {"subject": "mitochondrial genome engineering", "relationship": "increase", "target": "mitochondrial autonomy"}, {"subject": "mitochondrial genome engineering", "relationship": "increase", "target": "nuclear-encoded proteins"}, {"subject": "mitochondrial genome engineering", "relationship": "increase", "target": "functions"}, {"subject": "mitochondrial genome engineering", "relationship": "increase", "target": "nuclear-encoded proteins and functions"}], "timestamp": "2024-01-10T21:14:18.917824"}]