[{"file_id": "97c3de33990e4fc6b7d4b70866e4c93c", "article": "Chunk # 0.\n# Bibliography Recommendation Report\n\n## Research Question:\nWhat ethical guidelines and safety measures need to be established to responsibly pursue mitochondrial manipulation, especially in therapeutic applications \n---\n\n### Source 1: Ethical and Social Policy Considerations of Novel Techniques for Prevention of Maternal Transmission of Mitochondrial DNA Diseases\n- **Reference**: National Academies of Sciences, Engineering, and Medicine 2016 Mitochondrial Replacement Techniques: Ethical, Social, and Policy Considerations Washington, DC: The National Academies Press https://doi.org/10.17226/21871 - **Relevance**: This source provides a comprehensive analysis of the ethical, social, and policy considerations surrounding mitochondrial replacement techniques (MRT) It is directly relevant to the research question as it addresses the implications of manipulating mitochondrial content in children and descendants of female offspring - **Reliability**: The report is published by the National Academies of Sciences, Engineering, and Medicine, which is a reputable and authoritative institution The committee responsible for the report includes experts in the field, ensuring the reliability of the information - **Significance**: The report offers a framework for oversight of MRTs and develops recommendations for the FDA's consideration of investigational new drug applications It is significant for establishing ethical guidelines and safety measures for mitochondrial manipulation in therapy \n---\n\n### Source 2: Mitochondrial Replacement Approaches: Challenges for Clinical Implementation\n- **Reference**: Klopstock, T., Klopstock, B., & Prokisch, H (2016) Mitochondrial replacement approaches: challenges for clinical implementation Genome Medicine, 8, 126 https://doi.org/10.1186/s13073-016-0380-2 - **Relevance**: This editorial summary discusses the scientific, regulatory, and ethical challenges of mitochondrial replacement techniques It is relevant to the research question as it highlights the need for international consensus and controlled clinical trials - **Reliability**: Published in Genome Medicine, a peer-reviewed journal, the article is a credible source that provides insights from experts in the field - **Significance**: The source emphasizes the importance of avoiding uncontrolled proliferation of mitochondrial replacement techniques and the need for international governance structures, which is crucial for the development of ethical guidelines and safety measures \n---\n\n### Source 3: The Special Considerations of Gene Therapy for Mitochondrial Diseases\n- **Reference**: Slone, J., & Huang, T (2020) The special considerations of gene therapy for mitochondrial diseases npj Genomic Medicine, 5, 7 https://doi.org/10.1038/s41525-020-0116-5 - **Relevance**: This article discusses the specific challenges in using gene therapy and gene editing technologies for treating mitochondrial diseases It is relevant as it addresses the unique qualities of the mitochondrial organelle that must be considered in therapy - **Reliability**: npj Genomic Medicine is a reputable journal, and the article is written by researchers with expertise in the field, making it a reliable source - **Significance**: The source provides detailed information on the effectiveness of different gene editing technologies, such as TALENs and ZFNs, over CRISPR/Cas9 for mitochondrial diseases, which is significant for understanding the safety and efficacy of these therapies \n---\n\n### Source 4: Current Advances in Gene Therapy of Mitochondrial Diseases\n- **Reference**: Soldatov, V.O., Kubekina, M.V., Skorkina, M.Y et al (2022) Current advances in gene therapy of mitochondrial diseases Journal of Translational Medicine, 20, 562 https://doi.org/10.1186/s12967-022-03685-0 - **Relevance**: This article provides an update on the current advances in gene therapy for mitochondrial diseases, which is directly relevant to the research question - **Reliability**: The Journal of Translational Medicine is a peer-reviewed journal that publishes high-quality research, and the authors are credible experts in the field - **Significance**: The source discusses the potential of gene therapy in treating mitochondrial diseases and the associated challenges, which is significant for drafting ethical guidelines and safety measures \n---\n\n### Source 5: Safety of Mitochondrial Transfer/Transplantation: Is More Always Better - **Reference**: Cell and Bioscience (2022) Safety of mitochondrial transfer/transplantation: is more always better https://cellandbioscience.biomedcentral.com/articles/10.1186/s13578-022-00805-7 - **Relevance**: This source explores the safety concerns of mitochondrial transfer and transplantation, which is essential for the research question - **Reliability**: Cell and Bioscience is a peer-reviewed journal, ensuring the reliability of the content - **Significance**: The article discusses the risks and challenges of mitochondrial transfer, which is crucial for establishing safety measures in therapeutic applications \n---\n\n### Source 6: Mitochondrial Medicine Therapies: A Well-Reasoned Approach to Managing Primary Mitochondrial Disease\n- **Reference**: Parikh, S., Goldstein, A., Karaa, A., Koenig, M.K., Anselm, I., Brunel-Guitton, C., .. & Cohen, B.H (2017) Mitochondrial Medicine Therapies: A Well-Reasoned Approach to Managing Primary Mitochondrial Disease Current Treatment Options in Neurology, 19, 11 https://doi.org/10.1007/s11940-017-0446-0 - **Relevance**: This source discusses current treatment options and approaches to managing primary mitochondrial diseases, which is relevant to the research question - **Reliability**: Published in a peer-reviewed journal, the article is authored by a group of clinicians and researchers with expertise in mitochondrial medicine - **Significance**: The source provides a reasoned approach to treatment, including the use of mitochondrial cocktails, which is significant for understanding the clinical management of mitochondrial disease and the ethical considerations of treatment regimens", "summary": "**SPR:**\n\n1. Ethical guidelines and safety measures for mitochondrial manipulation in therapy need to be established. (Source 1)\n2. International consensus and controlled clinical trials are necessary for the implementation of mitochondrial replacement techniques. (Source 2)\n3. The unique qualities of the mitochondrial organelle must be considered in gene therapy for mitochondrial diseases. (Source 3)\n4. Current advances in gene therapy offer potential for treating mitochondrial diseases but come with associated challenges. (Source 4)\n5. Safety concerns regarding mitochondrial transfer and transplantation need to be addressed in therapeutic applications. (Source 5)\n6. A well-reasoned approach to managing primary mitochondrial disease includes the use of mitochondrial cocktails. (Source 6)", "clean_entities": [], "dirty_entities": ["Entities: National Academies of Sciences", "Engineering", "and Medicine", "MRT", "FDA", "Genome Medicine", "npj Genomic Medicine", "TALENs", "ZFNs", "CRISPR/Cas9", "Journal of Translational Medicine", "Cell and Bioscience", "Parikh", "Goldstein", "Karaa", "Koenig", "Anselm", "Brunel-Guitton", "Cohen", "", "Keywords: ethical guidelines", "safety measures", "mitochondrial manipulation", "therapeutic applications", "prevention of maternal transmission", "mitochondrial DNA diseases", "clinical implementation", "gene therapy", "gene editing technologies", "current advances", "mitochondrial transfer/transplantation", "primary mitochondrial disease", "treatment options", "mitochondrial cocktails", "", "Key Phrases: ethical", "social", "and policy considerations", "scientific", "regulatory", "and ethical challenges", "international consensus", "controlled clinical trials", "specific challenges in using gene therapy and gene editing technologies", "effectiveness of different gene editing technologies", "potential of gene therapy", "safety concerns", "current treatment options and approaches", "clinical management of mitochondrial disease", "reasoned approach to treatment", "", "References: National Academies of Sciences", "Engineering", "and Medicine 2016 Mitochondrial Replacement Techniques: Ethical", "Social", "and Policy Considerations", "Klopstock", "T.", "Klopstock", "B.", "& Prokisch", "H 2016 Mitochondrial Replacement Approaches: Challenges for Clinical Implementation", "Slone", "J.", "& Huang", "T 2020 The Special Considerations of Gene Therapy for Mitochondrial Diseases", "Soldatov", "V.O.", "Kubekina", "M.V.", "Skorkina", "M.Y et al 2022 Current Advances in Gene Therapy of Mitochondrial Diseases", "Cell and Bioscience 2022 Safety of Mitochondrial Transfer/Transplantation: Is More Always Better", "Parikh", "S.", "Goldstein", "A.", "Karaa", "A.", "Koenig", "M.K.", "Anselm", "I.", "Brunel-Guitton", "C.", ".. & Cohen", "B.H 2017 Mitochondrial Medicine Therapies: A Well-Reasoned Approach to Managing Primary Mitochondrial Disease", "", "Abstract Concepts: ethical guidelines", "safety measures", "mitochondrial manipulation", "therapeutic applications", "maternal transmission", "mitochondrial DNA diseases", "gene therapy", "gene editing technologies", "clinical implementation", "international consensus", "controlled clinical trials", "safety concerns", "clinical management", "treatment options", "reasoned approach"], "references": "", "topics": [{"topic": "Ethical guidelines and safety measures for mitochondrial manipulation in therapy", "justification": "The summary highlights the need for establishing ethical guidelines and safety measures for mitochondrial manipulation in therapy. This topic focuses on the ethical and safety considerations associated with mitochondrial manipulation."}, {"topic": "International consensus and controlled clinical trials for mitochondrial replacement techniques", "justification": "The summary emphasizes the necessity of international consensus and controlled clinical trials for the implementation of mitochondrial replacement techniques. This topic explores the importance of consensus and rigorous testing in the development and adoption of mitochondrial replacement techniques."}, {"topic": "Consideration of the unique qualities of the mitochondrial organelle in gene therapy for mitochondrial diseases", "justification": "The summary mentions the importance of considering the unique qualities of the mitochondrial organelle in gene therapy for mitochondrial diseases. This topic delves into the specific challenges and considerations related to targeting the mitochondrial organelle in gene therapy."}, {"topic": "Advances in gene therapy for treating mitochondrial diseases and associated challenges", "justification": "The summary discusses the current advances in gene therapy for treating mitochondrial diseases and the associated challenges. This topic explores the potential of gene therapy in treating mitochondrial diseases and the obstacles that need to be overcome."}, {"topic": "Addressing safety concerns regarding mitochondrial transfer and transplantation in therapeutic applications", "justification": "The summary highlights the need to address safety concerns regarding mitochondrial transfer and transplantation in therapeutic applications. This topic focuses on the safety considerations and potential risks associated with mitochondrial transfer and transplantation."}, {"topic": "Use of mitochondrial cocktails in managing primary mitochondrial disease", "justification": "The summary mentions the use of mitochondrial cocktails in managing primary mitochondrial disease. This topic explores the approach of using mitochondrial cocktails as a management strategy for primary mitochondrial disease."}], "hypothetical_questions": [{"question_type": "Content-Based Question", "question": "What are some of the key ethical considerations that need to be addressed when it comes to mitochondrial manipulation in therapy?"}, {"question_type": "Analytical Question", "question": "How can international consensus and controlled clinical trials contribute to the safe and effective implementation of mitochondrial replacement techniques?"}, {"question_type": "Creative/Scenario-Based Question", "question": "Imagine a scenario where gene therapy for mitochondrial diseases becomes widely accessible. What are some potential challenges that might arise in terms of ensuring the unique qualities of the mitochondrial organelle are considered?"}, {"question_type": "Contextual/Relational Question", "question": "How do the current advances in gene therapy for mitochondrial diseases relate to the safety concerns that need to be addressed in mitochondrial transfer and transplantation?"}, {"question_type": "User-Interactive Question", "question": "In your opinion, what would be the most effective approach to managing primary mitochondrial disease, taking into consideration the use of mitochondrial cocktails and other potential treatments?"}], "knowledge_triplets": [{"subject": "mitochondrial manipulation", "relationship": "responsible pursuit", "target": "therapeutic applications"}, {"subject": "mitochondrial replacement techniques", "relationship": "ethical", "target": "social, and policy considerations"}, {"subject": "mitochondrial content", "relationship": "children and descendants", "target": "female offspring"}, {"subject": "mitochondrial replacement techniques", "relationship": "challenges", "target": "clinical implementation"}, {"subject": "uncontrolled proliferation", "relationship": "mitochondrial replacement techniques", "target": "international governance structures"}, {"subject": "gene therapy", "relationship": "mitochondrial diseases", "target": "specific challenges"}, {"subject": "gene editing technologies", "relationship": "effectiveness", "target": "mitochondrial diseases"}, {"subject": "gene therapy", "relationship": "mitochondrial diseases", "target": "current advances"}, {"subject": "mitochondrial cocktails", "relationship": "clinical management", "target": "mitochondrial disease"}, {"subject": "mitochondrial manipulation", "relationship": "responsible pursuit", "target": "therapeutic applications"}, {"subject": "mitochondrial replacement techniques", "relationship": "ethical", "target": "social, and policy considerations"}, {"subject": "manipulating mitochondrial content", "relationship": "children and descendants", "target": "female offspring"}, {"subject": "mitochondrial replacement techniques", "relationship": "international consensus", "target": "controlled clinical trials"}, {"subject": "gene therapy", "relationship": "gene editing technologies", "target": "treating mitochondrial diseases"}, {"subject": "gene editing technologies", "relationship": "TALENs and ZFNs", "target": "CRISPR/Cas9"}, {"subject": "gene therapy", "relationship": "treating mitochondrial diseases", "target": "challenges"}, {"subject": "mitochondrial diseases", "relationship": "gene therapy", "target": "potential"}, {"subject": "gene therapy", "relationship": "mitochondrial diseases", "target": "challenges"}, {"subject": "primary mitochondrial disease", "relationship": "mitochondrial cocktails", "target": "clinical management"}, {"subject": "mitochondrial manipulation", "relationship": "responsible pursuit", "target": "therapeutic applications"}, {"subject": "mitochondrial replacement techniques", "relationship": "ethical", "target": "social, and policy considerations"}, {"subject": "manipulating mitochondrial content", "relationship": "children and descendants", "target": "female offspring"}, {"subject": "mitochondrial replacement techniques", "relationship": "international consensus", "target": "controlled clinical trials"}, {"subject": "gene therapy", "relationship": "gene editing technologies", "target": "treating mitochondrial diseases"}, {"subject": "gene editing technologies", "relationship": "TALENs and ZFNs", "target": "CRISPR/Cas9"}, {"subject": "gene therapy", "relationship": "treating mitochondrial diseases", "target": "challenges"}, {"subject": "mitochondrial diseases", "relationship": "gene therapy", "target": "potential"}, {"subject": "gene therapy", "relationship": "mitochondrial diseases", "target": "challenges"}, {"subject": "primary mitochondrial disease", "relationship": "mitochondrial cocktails", "target": "clinical management"}], "timestamp": "2024-01-10T21:20:51.466054"}, {"file_id": "97c3de33990e4fc6b7d4b70866e4c93c", "article": "Chunk # 1.\n\n---\n\n### Conclusion\nThe above sources provide a comprehensive foundation for establishing ethical guidelines and safety measures for mitochondrial manipulation in therapeutic applications They offer insights into the complexities of mitochondrial genetics, the challenges of clinical implementation, and the current advances in gene therapy The reliability of these sources is ensured by their publication in reputable journals and authorship by experts in the field The significance of these sources lies in their contribution to understanding the safety, efficacy, and ethical considerations of mitochondrial therapies, which is crucial for responsible development and application in biotechnology.", "summary": "- Comprehensive sources establish ethical guidelines and safety measures for mitochondrial manipulation in therapy.\n- Sources explore mitochondrial genetics, clinical challenges, and advancements in gene therapy.\n- Published in reputable journals and authored by experts, ensuring reliability.\n- Crucial for responsible development and application of mitochondrial therapies in biotechnology.", "clean_entities": [], "dirty_entities": ["Entities: ethical guidelines", "safety measures", "mitochondrial manipulation", "therapeutic applications", "mitochondrial genetics", "clinical implementation", "gene therapy", "reputable journals", "experts", "field", "safety", "efficacy", "ethical considerations", "mitochondrial therapies", "responsible development", "application", "biotechnology.", "", "Keywords: foundation", "establishing", "insights", "complexities", "challenges", "advances", "reliability", "publication", "significance", "understanding", "responsible.", "", "Key Phrases: ethical guidelines and safety measures", "mitochondrial manipulation in therapeutic applications", "complexities of mitochondrial genetics", "challenges of clinical implementation", "current advances in gene therapy", "publication in reputable journals", "authorship by experts in the field", "safety", "efficacy", "and ethical considerations of mitochondrial therapies", "responsible development and application in biotechnology.", "", "References: sources", "above sources.", "", "Abstract Concepts: ethical guidelines", "safety measures", "mitochondrial manipulation", "therapeutic applications", "complexities", "clinical implementation", "gene therapy", "reliability", "publication", "significance", "understanding", "responsible development", "application", "biotechnology.", "", "Final Output: ethical guidelines", "safety measures", "mitochondrial manipulation", "therapeutic applications", "mitochondrial genetics", "clinical implementation", "gene therapy", "reputable journals", "experts", "field", "safety", "efficacy", "ethical considerations", "mitochondrial therapies", "responsible development", "application", "biotechnology."], "references": "", "topics": [{"topic": "Ethical guidelines and safety measures for mitochondrial manipulation in therapy", "justification": "The summary mentions that comprehensive sources establish ethical guidelines and safety measures for mitochondrial manipulation in therapy. This topic is important as it addresses the ethical considerations and safety precautions associated with mitochondrial manipulation in therapy."}, {"topic": "Mitochondrial genetics and clinical challenges", "justification": "The summary states that sources explore mitochondrial genetics and clinical challenges. This topic focuses on the genetic aspects of mitochondria and the challenges faced in clinical settings, providing insights into the scientific and medical aspects of mitochondrial therapy."}, {"topic": "Advancements in gene therapy for mitochondrial disorders", "justification": "The summary mentions advancements in gene therapy. This topic highlights the progress made in gene therapy specifically for treating mitochondrial disorders, indicating the potential for new treatment options."}, {"topic": "Reliability of published sources and expertise of authors", "justification": "The summary states that the sources are published in reputable journals and authored by experts, ensuring reliability. This topic emphasizes the importance of reliable and credible sources in the field of mitochondrial therapy, which is crucial for responsible development and application of these therapies in biotechnology."}], "hypothetical_questions": [{"question_type": "Content-Based Question", "question": "What are some of the ethical guidelines and safety measures that comprehensive sources establish for mitochondrial manipulation in therapy?"}, {"question_type": "Analytical Question", "question": "How do sources explore the clinical challenges associated with mitochondrial genetics and advancements in gene therapy?"}, {"question_type": "Creative/Scenario-Based Question", "question": "Imagine a future where mitochondrial therapies have been widely developed and applied in biotechnology. What are some potential benefits and risks that need to be considered?"}, {"question_type": "Contextual/Relational Question", "question": "How do the published sources contribute to the responsible development and application of mitochondrial therapies in biotechnology?"}, {"question_type": "User-Interactive Question", "question": "What are your thoughts on the importance of ethical guidelines and safety measures in the development and application of mitochondrial therapies in therapy? How do you think these measures can ensure responsible practices?"}], "knowledge_triplets": [{"subject": "sources", "relationship": "provide a comprehensive foundation for", "target": "establishing ethical guidelines and safety measures"}, {"subject": "mitochondrial manipulation", "relationship": "in therapeutic applications", "target": "offer insights into the complexities of mitochondrial genetics"}, {"subject": "clinical implementation", "relationship": "challenges of", "target": "current advances in gene therapy"}, {"subject": "reliability of these sources", "relationship": "ensured by", "target": "publication in reputable journals"}, {"subject": "reliability of these sources", "relationship": "ensured by", "target": "authorship by experts in the field"}, {"subject": "significance of these sources", "relationship": "lies in", "target": "contribution to understanding the safety, efficacy, and ethical considerations of mitochondrial therapies"}, {"subject": "contribution to understanding the safety", "relationship": "efficacy", "target": "and ethical considerations of mitochondrial therapies, crucial for, responsible development and application in biotechnology"}, {"subject": "ethical guidelines", "relationship": "establish", "target": "safety measures"}, {"subject": "mitochondrial manipulation", "relationship": "therapeutic applications", "target": "mitochondrial genetics"}, {"subject": "mitochondrial manipulation", "relationship": "therapeutic applications", "target": "clinical implementation"}, {"subject": "mitochondrial manipulation", "relationship": "therapeutic applications", "target": "gene therapy"}, {"subject": "mitochondrial manipulation", "relationship": "therapeutic applications", "target": "reputable journals"}, {"subject": "mitochondrial manipulation", "relationship": "therapeutic applications", "target": "experts"}, {"subject": "mitochondrial manipulation", "relationship": "therapeutic applications", "target": "field"}, {"subject": "mitochondrial manipulation", "relationship": "therapeutic applications", "target": "safety"}, {"subject": "mitochondrial manipulation", "relationship": "therapeutic applications", "target": "efficacy"}, {"subject": "mitochondrial manipulation", "relationship": "therapeutic applications", "target": "ethical considerations"}, {"subject": "mitochondrial manipulation", "relationship": "therapeutic applications", "target": "mitochondrial therapies"}, {"subject": "mitochondrial manipulation", "relationship": "therapeutic applications", "target": "responsible development"}, {"subject": "mitochondrial manipulation", "relationship": "therapeutic applications", "target": "application"}, {"subject": "mitochondrial manipulation", "relationship": "therapeutic applications", "target": "biotechnology"}, {"subject": "sources", "relationship": "provide a comprehensive foundation for", "target": "establishing ethical guidelines and safety measures"}, {"subject": "mitochondrial manipulation", "relationship": "in therapeutic applications", "target": "offer insights into the complexities of mitochondrial genetics"}, {"subject": "clinical implementation", "relationship": "challenges of", "target": "current advances in gene therapy"}, {"subject": "reliability of these sources", "relationship": "ensured by", "target": "publication in reputable journals"}, {"subject": "reliability of these sources", "relationship": "ensured by", "target": "authorship by experts in the field"}, {"subject": "significance of these sources", "relationship": "lies in", "target": "contribution to understanding the safety, efficacy, and ethical considerations of mitochondrial therapies"}, {"subject": "contribution to understanding the safety", "relationship": "efficacy", "target": "and ethical considerations of mitochondrial therapies, crucial for, responsible development and application in biotechnology"}, {"subject": "ethical guidelines", "relationship": "establish", "target": "safety measures"}, {"subject": "mitochondrial manipulation", "relationship": "therapeutic applications", "target": "mitochondrial genetics"}, {"subject": "mitochondrial manipulation", "relationship": "therapeutic applications", "target": "clinical implementation"}, {"subject": "mitochondrial manipulation", "relationship": "therapeutic applications", "target": "gene therapy"}, {"subject": "mitochondrial manipulation", "relationship": "therapeutic applications", "target": "reputable journals"}, {"subject": "mitochondrial manipulation", "relationship": "therapeutic applications", "target": "experts"}, {"subject": "mitochondrial manipulation", "relationship": "therapeutic applications", "target": "field"}, {"subject": "mitochondrial manipulation", "relationship": "therapeutic applications", "target": "safety"}, {"subject": "mitochondrial manipulation", "relationship": "therapeutic applications", "target": "efficacy"}, {"subject": "mitochondrial manipulation", "relationship": "therapeutic applications", "target": "ethical considerations"}, {"subject": "mitochondrial manipulation", "relationship": "therapeutic applications", "target": "mitochondrial therapies"}, {"subject": "mitochondrial manipulation", "relationship": "therapeutic applications", "target": "responsible development"}, {"subject": "mitochondrial manipulation", "relationship": "therapeutic applications", "target": "application"}, {"subject": "mitochondrial manipulation", "relationship": "therapeutic applications", "target": "biotechnology"}], "timestamp": "2024-01-10T21:21:20.080332"}]