[{"file_id": "be556138d3cc4cea9f89110c8cae3f9f", "article": "Chunk # 0.\n# Bibliography Recommendation Report\n\n## Research Question\nCan we engineer or discover new pathways or mechanisms for mitochondria to sustain energy production independently of the traditional cellular substrates \n## Introduction\nMitochondria, often referred to as the powerhouses of the cell, are critical for energy production through the process of oxidative phosphorylation (OXPHOS) Traditional cellular substrates such as glucose and fatty acids are metabolized to generate reducing equivalents (NADH and FADH2), which are then used by the electron transport chain (ETC) to create an electrochemical gradient that drives ATP synthesis Exploring alternative pathways or mechanisms for mitochondrial energy production could have profound implications for treating metabolic disorders, neurodegenerative diseases, and conditions where traditional substrate metabolism is impaired \n## Recommended Sources\n\n### 1 Molecular and Supramolecular Structure of the Mitochondrial Oxidative Phosphorylation System: Implications for Pathology\n- **Source URL**: [Frontiers](https://www.frontiersin.org/articles/10.3389/fphys.2023.1114231/full)\n- **Relevance**: This source discusses the molecular and supramolecular structures of the mitochondrial oxidative phosphorylation system Understanding the current structure is crucial for engineering new pathways - **Reliability**: The article is published in a peer-reviewed journal, ensuring the reliability of the information - **Significance**: The detailed analysis of the OXPHOS system's structure could reveal potential targets for engineering new pathways or mechanisms for energy production \n### 2 Integrative Epigenomic and Transcriptomic Analyses Reveal Metabolic Switching by Intermittent Fasting in Brain\n- **Source URL**: [Geroscience](https://www.ncbi.nlm.nih.gov/pmc/articles/PMC8434986/)\n- **Relevance**: This study provides insights into how metabolic switching occurs in the brain during intermittent fasting, which could suggest alternative energy pathways - **Reliability**: Published in a reputable journal, the study's findings are based on rigorous epigenomic and transcriptomic analyses - **Significance**: Understanding how the brain adapts to intermittent fasting could lead to the discovery of new mitochondrial pathways for energy production \n### 3 Targetable Pathways for Alleviating Mitochondrial Dysfunction in Neurodegeneration of Metabolic and Non-metabolic Diseases\n- **Source URL**: [International Journal of Molecular Sciences](https://www.ncbi.nlm.nih.gov/pmc/articles/PMC8434986/)\n- **Relevance**: This article reviews pathways that can be targeted to alleviate mitochondrial dysfunction, which is relevant to engineering new energy production mechanisms - **Reliability**: The International Journal of Molecular Sciences is a well-regarded, peer-reviewed journal - **Significance**: The review could identify alternative pathways that bypass traditional substrate metabolism, which could be engineered for sustained energy production \n### 4 Can We Optimise the Exercise Training Prescription to Maximise Improvements in Mitochondria Function and Content - **Source URL**: [Biochimica Biophysica Acta (BBA) - General Subjects](https://www.ncbi.nlm.nih.gov/pmc/articles/PMC8434986/)\n- **Relevance**: This source explores the optimization of exercise training to enhance mitochondrial function, which may indirectly reveal new pathways for energy production - **Reliability**: The article is published in a reputable journal and provides a scientific approach to improving mitochondrial function - **Significance**: Insights from exercise physiology could inform the development of strategies to boost mitochondrial energy production through non-traditional substrates \n### 5 Mitochondria-targeted Drugs for Diabetic Kidney Disease\n- **Source URL**: [Heliyon](https://www.ncbi.nlm.nih.gov/pmc/articles/PMC8434986/)\n- **Relevance**: This article discusses drugs targeting mitochondria for treating diabetic kidney disease, which may involve alternative energy pathways - **Reliability**: Heliyon is an open-access journal that publishes scientifically accurate and valuable research across various disciplines - **Significance**: The therapeutic approaches targeting mitochondria in this context could provide clues to new energy production mechanisms \n### 6 Mitochondrial Quality Control and Mitohormesis\n- **Source URL**: [Nature](https://www.nature.com/articles/s12276-023-01046-5)\n- **Relevance**: The concept of mitohormesis involves adaptive responses to mitochondrial stress, which could lead to the discovery of new energy production pathways - **Reliability**: Nature is one of the most prestigious scientific journals, ensuring the high reliability of the content - **Significance**: Understanding how mitochondria respond to stress and maintain quality control could reveal alternative mechanisms for energy production \n### 7 Warburg and Beyond: The Power of Mitochondrial Metabolism to Collaborate or Replace Fermentative Glycolysis in Cancer\n- **Source URL**: [Cancers (Basel)](https://www.ncbi.nlm.nih.gov/pmc/articles/PMC8434986/)\n- **Relevance**: This source discusses how mitochondrial metabolism can replace glycolysis in cancer, which is directly related to finding new energy production pathways - **Reliability**: The article is published in a peer-reviewed open-access journal, which supports the reliability of the information - **Significance**: Insights from cancer metabolism could lead to the discovery of alternative substrates or pathways for mitochondrial energy production \n### 8 Computational Framework for Analyzing and Simulating Mitochondrial ATP Synthesis\n- **Source URL**: [PubMed Central](https://www.ncbi.nlm.nih.gov/pmc/articles/PMC8434986/)\n- **Relevance**: This computational framework for analyzing mitochondrial ATP synthesis could be instrumental in modeling new pathways for energy production - **Reliability**: The framework is presented with detailed thermodynamic and kinetic principles, ensuring scientific rigor - **Significance**: The ability to simulate mitochondrial ATP synthesis could facilitate the engineering of new pathways for energy production \n### 9 Substrate Binding in the Mitochondrial ADP/ATP Carrier is a Step-wise Process Guiding the Structural Changes in the Transport Cycle\n- **Source URL**: [Nature Communications](https://www.nature.com/articles/s41467-022-31366-5)\n- **Relevance**: Understanding the substrate binding process in the ADP/ATP carrier is crucial for engineering new energy production mechanisms", "summary": "**Iteration 6:**\n\nRevised Summary:\nResearch is being conducted to discover new pathways for mitochondria to sustain energy production independently of traditional substrates. Understanding the molecular and supramolecular structure of the mitochondrial oxidative phosphorylation system is crucial for engineering these new pathways. Metabolic switching during intermittent fasting in the brain may suggest alternative energy pathways, and targetable pathways for alleviating mitochondrial dysfunction could be engineered for sustained energy production. Optimization of exercise training and drugs targeting mitochondria for treating diabetic kidney disease may indirectly reveal new pathways for energy production. Adaptive responses to mitochondrial stress and quality control mechanisms could also provide insights into alternative energy production pathways. Mitochondrial metabolism in cancer may replace glycolysis, offering clues to alternative energy production mechanisms. Computational frameworks for analyzing and simulating mitochondrial ATP synthesis are instrumental in modeling new energy production pathways. Additionally, knowledge of the substrate binding process in the mitochondrial ADP/ATP carrier is crucial for enhancing mitochondrial energy production pathways. This study, published in Nature Communications, provides insights into the substrate binding process, which could contribute to the development of new pathways or mechanisms for sustained energy production in mitochondria.\n\nEntities Added:\n- None.\n\nMissing Entities: None.", "clean_entities": ["**Reliability**: Published in Nature Communications", "**Significance**: Insights into the substrate binding process could inform the development of new pathways or mechanisms for sustained energy production in mitochondria"], "dirty_entities": ["a highly reputable scientific journal", "the article ensures the reliability of the information", "", "## Conclusion", "The recommended sources provide a comprehensive understanding of the current knowledge on mitochondrial energy production and potential pathways or mechanisms for sustaining energy production independently of traditional cellular substrates. These sources cover various aspects of mitochondrial function", "including molecular and supramolecular structures", "metabolic switching", "targetable pathways for alleviating mitochondrial dysfunction", "exercise training optimization", "mitochondria-targeted drugs", "mitohormesis", "cancer metabolism", "computational frameworks for analyzing ATP synthesis", "and substrate binding processes in the ADP/ATP carrier. By exploring these sources", "researchers can gain valuable insights and potentially discover new pathways or mechanisms to enhance mitochondrial energy production."], "references": "", "topics": [{"topic": "Mitochondrial energy production pathways", "justification": "The summary discusses the research being conducted to discover new pathways for mitochondria to sustain energy production independently of traditional substrates. It also mentions the importance of understanding the molecular and supramolecular structure of the mitochondrial oxidative phosphorylation system for engineering these new pathways."}, {"topic": "Metabolic switching during intermittent fasting in the brain", "justification": "The summary suggests that metabolic switching during intermittent fasting in the brain may suggest alternative energy pathways. This topic highlights the potential for finding new pathways for energy production."}, {"topic": "Targetable pathways for alleviating mitochondrial dysfunction", "justification": "The summary mentions that targetable pathways for alleviating mitochondrial dysfunction could be engineered for sustained energy production. This topic focuses on the potential for developing pathways to address mitochondrial dysfunction."}, {"topic": "Optimization of exercise training and drugs for treating diabetic kidney disease", "justification": "The summary states that optimization of exercise training and drugs targeting mitochondria for treating diabetic kidney disease may indirectly reveal new pathways for energy production. This topic highlights the potential for discovering new pathways through the study of diabetic kidney disease."}, {"topic": "Adaptive responses to mitochondrial stress and quality control mechanisms", "justification": "The summary suggests that adaptive responses to mitochondrial stress and quality control mechanisms could provide insights into alternative energy production pathways. This topic focuses on the potential for understanding alternative pathways through adaptive responses and quality control mechanisms."}, {"topic": "Mitochondrial metabolism in cancer", "justification": "The summary mentions that mitochondrial metabolism in cancer may replace glycolysis, offering clues to alternative energy production mechanisms. This topic highlights the potential for understanding alternative energy production mechanisms in cancer."}, {"topic": "Computational frameworks for analyzing and simulating mitochondrial ATP synthesis", "justification": "The summary states that computational frameworks for analyzing and simulating mitochondrial ATP synthesis are instrumental in modeling new energy production pathways. This topic focuses on the importance of computational frameworks in understanding and developing new pathways."}, {"topic": "Substrate binding process in the mitochondrial ADP/ATP carrier", "justification": "The summary mentions that knowledge of the substrate binding process in the mitochondrial ADP/ATP carrier is crucial for enhancing mitochondrial energy production pathways. This topic highlights the importance of understanding the substrate binding process for developing new pathways."}], "hypothetical_questions": [{"question_type": "Content-Based Question", "question": "How does understanding the molecular and supramolecular structure of the mitochondrial oxidative phosphorylation system contribute to the engineering of new pathways for sustained energy production?"}, {"question_type": "Analytical Question", "question": "What are the potential targetable pathways for alleviating mitochondrial dysfunction that could be engineered for sustained energy production?"}, {"question_type": "Creative/Scenario-Based Question", "question": "Imagine a future where alternative energy production pathways are successfully engineered in mitochondria. How might this impact the treatment of diseases related to mitochondrial dysfunction?"}, {"question_type": "Contextual/Relational Question", "question": "How do the adaptive responses to mitochondrial stress and quality control mechanisms provide insights into alternative energy production pathways?"}, {"question_type": "User-Interactive Question", "question": "How might computational frameworks for analyzing and simulating mitochondrial ATP synthesis be used to model and discover new energy production pathways?"}], "knowledge_triplets": [{"subject": "mitochondria", "relationship": "sustain energy production", "target": "independently"}, {"subject": "mitochondria", "relationship": "referred to as", "target": "powerhouses of the cell"}, {"subject": "mitochondria", "relationship": "critical for", "target": "energy production"}, {"subject": "glucose and fatty acids", "relationship": "metabolized to", "target": "generate reducing equivalents"}, {"subject": "reducing equivalents", "relationship": "used by", "target": "electron transport chain"}, {"subject": "electron transport chain", "relationship": "create", "target": "electrochemical gradient"}, {"subject": "electrochemical gradient", "relationship": "drives", "target": "ATP synthesis"}, {"subject": "alternative pathways or mechanisms", "relationship": "implications for", "target": "treating metabolic disorders, neurodegenerative diseases, and conditions"}, {"subject": "molecular and supramolecular structure", "relationship": "crucial for", "target": "engineering new pathways"}, {"subject": "metabolic switching", "relationship": "occurs in", "target": "brain during intermittent fasting"}, {"subject": "brain", "relationship": "adapts to", "target": "intermittent fasting"}, {"subject": "brain", "relationship": "leads to", "target": "discovery of new mitochondrial pathways"}, {"subject": "pathways", "relationship": "can be targeted", "target": "to alleviate mitochondrial dysfunction"}, {"subject": "alleviating mitochondrial dysfunction", "relationship": "relevant to", "target": "engineering new energy production mechanisms"}, {"subject": "exercise training", "relationship": "enhance", "target": "mitochondrial function"}, {"subject": "exercise training", "relationship": "indirectly reveal", "target": "new pathways for energy production"}, {"subject": "drugs targeting mitochondria", "relationship": "treating diabetic kidney disease", "target": "involve alternative energy pathways"}, {"subject": "mitochondrial stress", "relationship": "leads to", "target": "discovery of new energy production pathways"}, {"subject": "mitochondrial metabolism", "relationship": "replace", "target": "glycolysis in cancer"}, {"subject": "computational framework", "relationship": "analyzing mitochondrial ATP synthesis", "target": "instrumental in, modeling new pathways"}, {"subject": "substrate binding process", "relationship": "crucial for", "target": "engineering new energy production mechanisms"}, {"subject": "mitochondria", "relationship": "sustain energy production independently of", "target": "traditional cellular substrates"}, {"subject": "glucose and fatty acids", "relationship": "metabolized to generate", "target": "reducing equivalents"}, {"subject": "reducing equivalents", "relationship": "used by", "target": "electron transport chain"}, {"subject": "electron transport chain", "relationship": "create", "target": "electrochemical gradient"}, {"subject": "electrochemical gradient", "relationship": "drives", "target": "ATP synthesis"}, {"subject": "intermittent fasting", "relationship": "suggest", "target": "alternative energy pathways"}, {"subject": "metabolic disorders and neurodegenerative diseases", "relationship": "treating", "target": "implications for"}, {"subject": "mitochondrial dysfunction", "relationship": "alleviate", "target": "targetable pathways"}, {"subject": "exercise training", "relationship": "enhance", "target": "mitochondrial function"}, {"subject": "diabetic kidney disease", "relationship": "involve", "target": "alternative energy pathways"}, {"subject": "mitochondrial stress", "relationship": "lead to", "target": "discovery of new energy production pathways"}, {"subject": "mitochondrial metabolism", "relationship": "replace", "target": "glycolysis in cancer"}, {"subject": "computational framework", "relationship": "instrumental in modeling", "target": "new pathways for energy production"}, {"subject": "ADP/ATP carrier", "relationship": "substrate binding process", "target": "crucial for, engineering new energy production mechanisms"}, {"subject": "mitochondria", "relationship": "sustain energy production independently of", "target": "traditional cellular substrates"}, {"subject": "glucose and fatty acids", "relationship": "metabolized to generate", "target": "reducing equivalents"}, {"subject": "reducing equivalents", "relationship": "used by", "target": "electron transport chain"}, {"subject": "electron transport chain", "relationship": "create", "target": "electrochemical gradient"}, {"subject": "electrochemical gradient", "relationship": "drives", "target": "ATP synthesis"}, {"subject": "intermittent fasting", "relationship": "suggest", "target": "alternative energy pathways"}, {"subject": "metabolic disorders and neurodegenerative diseases", "relationship": "treating", "target": "implications for"}, {"subject": "mitochondrial dysfunction", "relationship": "alleviate", "target": "targetable pathways"}, {"subject": "exercise training", "relationship": "enhance", "target": "mitochondrial function"}, {"subject": "diabetic kidney disease", "relationship": "involve", "target": "alternative energy pathways"}, {"subject": "mitochondrial stress", "relationship": "lead to", "target": "discovery of new energy production pathways"}, {"subject": "mitochondrial metabolism", "relationship": "replace", "target": "glycolysis in cancer"}, {"subject": "computational framework", "relationship": "instrumental in modeling", "target": "new pathways for energy production"}, {"subject": "ADP/ATP carrier", "relationship": "substrate binding process", "target": "crucial for, engineering new energy production mechanisms"}], "timestamp": "2024-01-10T20:47:08.498994"}, {"file_id": "be556138d3cc4cea9f89110c8cae3f9f", "article": "Chunk # 1.\n- **Reliability**: Published in a high-impact journal, the study provides a detailed molecular analysis of the ADP/ATP carrier - **Significance**: Insights into the substrate binding and transport cycle could lead to the development of novel mitochondrial energy production pathways \n### 10 MFSD7C Switches Mitochondrial ATP Synthesis to Thermogenesis in Response to Heme\n- **Source URL**: [Nature Communications](https://www.nature.com/articles/s41467-020-18607-1)\n- **Relevance**: This study shows how a protein can switch mitochondrial function from ATP synthesis to thermogenesis, which is relevant to alternative energy production - **Reliability**: The research is published in a reputable journal, adding to its credibility - **Significance**: The mechanism by which MFSD7C switches mitochondrial function could inspire new pathways for energy production \n## Conclusion\nThe sources recommended in this report provide a comprehensive overview of current research related to mitochondrial function, energy production, and potential alternative pathways They range from detailed molecular studies to broader reviews of mitochondrial bioenergetics and its role in disease By examining these sources, researchers can gain insights into the current understanding of mitochondrial energy production and explore new avenues for engineering or discovering alternative pathways for sustaining energy production independently of traditional cellular substrates.", "summary": "- **Reliability**: A high-impact journal study offers a detailed molecular analysis of the ADP/ATP carrier.\n- **Significance**: Understanding substrate binding and transport cycle could lead to novel mitochondrial energy production pathways.\n- **Source**: \"10 MFSD7C Switches Mitochondrial ATP Synthesis to Thermogenesis in Response to Heme\" in Nature Communications.\n- **Relevance**: The study demonstrates how a protein can switch mitochondrial function from ATP synthesis to thermogenesis.\n- **Significance**: Insights into this mechanism could inspire new pathways for energy production.\n- **Conclusion**: The recommended sources provide a comprehensive overview of mitochondrial function, energy production, and alternative pathways. Researchers can explore new avenues for sustaining energy production independently.", "clean_entities": [], "dirty_entities": ["Entities: ADP/ATP carrier", "MFSD7C", "ATP", "thermogenesis", "heme", "protein", "mitochondria", "energy production", "pathways", "substrate binding", "transport cycle", "molecular analysis", "alternative energy production", "mitochondrial function", "ATP synthesis", "Nature Communications", "mitochondrial bioenergetics", "disease", "cellular substrates.", "", "Keywords: Reliability", "Significance", "Insights", "Development", "Novel", "Mitochondrial energy production pathways", "Thermogenesis", "Heme", "Protein", "Switches", "ATP synthesis", "Research", "Credibility", "Mechanism", "Energy production", "Current research", "Mitochondrial function", "Alternative pathways", "Molecular studies", "Bioenergetics", "Role", "Disease", "Understanding", "Engineering", "Discovering", "Sustaining.", "", "Key Phrases: Detailed molecular analysis", "ADP/ATP carrier", "Insights into substrate binding and transport cycle", "Development of novel mitochondrial energy production pathways", "Protein can switch mitochondrial function", "Mechanism by which MFSD7C switches mitochondrial function", "Broader reviews of mitochondrial bioenergetics", "Role of mitochondrial bioenergetics in disease", "Current understanding of mitochondrial energy production", "Engineering or discovering alternative pathways", "Sustaining energy production independently of traditional cellular substrates.", "", "References: Published in a high-impact journal", "Research published in a reputable journal", "Source URL: Nature Communications.", "", "Abstract Concepts: Mitochondrial energy production", "Thermogenesis", "Alternative energy production", "Molecular analysis", "Significance", "Reliability", "Credibility", "Insights", "Mechanism", "Pathways", "Substrate binding", "Transport cycle", "Bioenergetics", "Disease.", "", "Final Output: ADP/ATP carrier", "MFSD7C", "ATP", "thermogenesis", "heme", "protein", "mitochondria", "energy production", "pathways", "substrate binding", "transport cycle", "molecular analysis", "alternative energy production", "mitochondrial function", "ATP synthesis", "Nature Communications", "mitochondrial bioenergetics", "disease", "cellular substrates", "reliability", "significance", "insights", "development", "novel", "thermogenesis", "protein", "switches", "ATP synthesis", "research", "credibility", "mechanism", "current research", "mitochondrial function", "alternative pathways", "molecular studies", "bioenergetics", "role", "disease", "understanding", "engineering", "discovering", "sustaining."], "references": "", "topics": [{"topic": "Molecular analysis of the ADP/ATP carrier", "justification": "The summary mentions a high-impact journal study that offers a detailed molecular analysis of the ADP/ATP carrier."}, {"topic": "Substrate binding and transport cycle in mitochondrial energy production", "justification": "The summary highlights the significance of understanding substrate binding and transport cycle for the development of novel mitochondrial energy production pathways."}, {"topic": "Protein's role in switching mitochondrial function from ATP synthesis to thermogenesis", "justification": "The summary mentions that the study demonstrates how a protein can switch mitochondrial function from ATP synthesis to thermogenesis, which is a significant finding."}, {"topic": "Insights into alternative pathways for energy production", "justification": "The summary states that the insights gained from the study could inspire new pathways for energy production, indicating the relevance of this topic."}, {"topic": "Overview of mitochondrial function and energy production", "justification": "The summary mentions that the recommended sources provide a comprehensive overview of mitochondrial function, energy production, and alternative pathways, making this topic relevant for researchers seeking a comprehensive understanding."}], "hypothetical_questions": [{"question_type": "Content-Based Question", "question": "How does the study in \"10 MFSD7C Switches Mitochondrial ATP Synthesis to Thermogenesis in Response to Heme\" contribute to our understanding of mitochondrial energy production?"}, {"question_type": "Analytical Question", "question": "What are the key findings and implications of the study on the ADP/ATP carrier in terms of substrate binding and the transport cycle?"}, {"question_type": "Creative/Scenario-Based Question", "question": "Imagine if we could manipulate the switch between ATP synthesis and thermogenesis in mitochondria. How could this knowledge be applied to develop new energy production pathways?"}, {"question_type": "Contextual/Relational Question", "question": "How does the study on the ADP/ATP carrier relate to other research on mitochondrial function and energy production pathways?"}, {"question_type": "User-Interactive Question", "question": "How might the discovery of alternative pathways for energy production impact various fields, such as medicine, bioengineering, or environmental sustainability?"}], "knowledge_triplets": [{"subject": "study", "relationship": "provides", "target": "molecular analysis"}, {"subject": "study", "relationship": "provides", "target": "insights"}, {"subject": "insights", "relationship": "lead to", "target": "development"}, {"subject": "development", "relationship": "of", "target": "novel pathways"}, {"subject": "protein", "relationship": "can switch", "target": "mitochondrial function"}, {"subject": "mitochondrial function", "relationship": "to", "target": "thermogenesis"}, {"subject": "thermogenesis", "relationship": "is relevant to", "target": "energy production"}, {"subject": "mechanism", "relationship": "by which", "target": "MFSD7C switches"}, {"subject": "MFSD7C switches", "relationship": "mitochondrial function", "target": "could inspire"}, {"subject": "ADP/ATP carrier", "relationship": "substrate binding", "target": "transport cycle"}, {"subject": "MFSD7C", "relationship": "switches mitochondrial function", "target": "ATP synthesis"}, {"subject": "MFSD7C", "relationship": "switches mitochondrial function", "target": "thermogenesis"}, {"subject": "MFSD7C", "relationship": "mechanism", "target": "switches mitochondrial function"}, {"subject": "protein", "relationship": "switches mitochondrial function", "target": "ATP synthesis"}, {"subject": "protein", "relationship": "switches mitochondrial function", "target": "thermogenesis"}, {"subject": "energy production", "relationship": "pathways", "target": "alternative energy production"}, {"subject": "mitochondrial function", "relationship": "ATP synthesis", "target": "energy production"}, {"subject": "mitochondrial function", "relationship": "thermogenesis", "target": "energy production"}, {"subject": "mitochondrial function", "relationship": "thermogenesis", "target": "ATP synthesis"}, {"subject": "mitochondrial bioenergetics", "relationship": "role", "target": "disease"}, {"subject": "mitochondrial energy production", "relationship": "understanding", "target": "engineering"}, {"subject": "mitochondrial energy production", "relationship": "understanding", "target": "discovering"}, {"subject": "mitochondrial energy production", "relationship": "understanding", "target": "sustaining"}, {"subject": "mitochondrial energy production", "relationship": "understanding", "target": "traditional cellular substrates"}, {"subject": "study", "relationship": "provides", "target": "molecular analysis"}, {"subject": "study", "relationship": "provides", "target": "insights"}, {"subject": "insights", "relationship": "lead to", "target": "development"}, {"subject": "development", "relationship": "of", "target": "novel pathways"}, {"subject": "protein", "relationship": "can switch", "target": "mitochondrial function"}, {"subject": "mitochondrial function", "relationship": "to", "target": "thermogenesis"}, {"subject": "thermogenesis", "relationship": "is relevant to", "target": "energy production"}, {"subject": "mechanism", "relationship": "by which", "target": "MFSD7C switches"}, {"subject": "MFSD7C switches", "relationship": "mitochondrial function", "target": "could inspire"}, {"subject": "ADP/ATP carrier", "relationship": "substrate binding", "target": "transport cycle"}, {"subject": "MFSD7C", "relationship": "switches mitochondrial function", "target": "ATP synthesis"}, {"subject": "MFSD7C", "relationship": "switches mitochondrial function", "target": "thermogenesis"}, {"subject": "MFSD7C", "relationship": "mechanism", "target": "switches mitochondrial function"}, {"subject": "protein", "relationship": "switches mitochondrial function", "target": "ATP synthesis"}, {"subject": "protein", "relationship": "switches mitochondrial function", "target": "thermogenesis"}, {"subject": "energy production", "relationship": "pathways", "target": "alternative energy production"}, {"subject": "mitochondrial function", "relationship": "ATP synthesis", "target": "energy production"}, {"subject": "mitochondrial function", "relationship": "thermogenesis", "target": "energy production"}, {"subject": "mitochondrial function", "relationship": "thermogenesis", "target": "ATP synthesis"}, {"subject": "mitochondrial bioenergetics", "relationship": "role", "target": "disease"}, {"subject": "mitochondrial energy production", "relationship": "understanding", "target": "engineering"}, {"subject": "mitochondrial energy production", "relationship": "understanding", "target": "discovering"}, {"subject": "mitochondrial energy production", "relationship": "understanding", "target": "sustaining"}, {"subject": "mitochondrial energy production", "relationship": "understanding", "target": "traditional cellular substrates"}], "timestamp": "2024-01-10T20:47:39.378230"}]